{"version":1.2,"sizeData":[{"is_predeco_product_template":false,"qty":7,"id":439,"refid":0,"addedprice":"0.43","simple_product":{"xe_color":"Heliconia","xe_size":"L","simpleProductId":"1417"}},{"is_predeco_product_template":false,"qty":7,"id":439,"refid":0,"addedprice":"0.43","simple_product":{"xe_color":"Heliconia","xe_size":"M","simpleProductId":"1418"}},{"is_predeco_product_template":false,"qty":0,"id":439,"refid":0,"addedprice":"0.43","simple_product":{"xe_color":"Heliconia","xe_size":"S","simpleProductId":"1419"}},{"is_predeco_product_template":false,"qty":0,"id":439,"refid":0,"addedprice":"0.43","simple_product":{"xe_color":"Heliconia","xe_size":"XL","simpleProductId":"1424"}},{"is_predeco_product_template":false,"qty":0,"id":439,"refid":0,"addedprice":"0.43","simple_product":{"xe_color":"Heliconia","xe_size":"2XL","simpleProductId":"1422"}},{"is_predeco_product_template":false,"qty":0,"id":439,"refid":0,"addedprice":"0.43","simple_product":{"xe_color":"Heliconia","xe_size":"3XL","simpleProductId":"1420"}},{"is_predeco_product_template":false,"qty":0,"id":439,"refid":0,"addedprice":"0.43","simple_product":{"xe_color":"Heliconia","xe_size":"4XL","simpleProductId":"1423"}},{"is_predeco_product_template":false,"qty":0,"id":439,"refid":0,"addedprice":"0.43","simple_product":{"xe_color":"Heliconia","xe_size":"5XL","simpleProductId":"1421"}}],"printType":"Screenprinting","printTypeId":"1","productInfo":{"productId":439,"variantId":"1417"},"sides":[{"url":"https://www.screenshotsinc.com//designer-tool/designer-assets/screenshotsinc_com/images/productTemplate/16/48.png","svg":"<svg width=\"500\" height=\"500\" xmlns=\"http://www.w3.org/2000/svg\" xmlns:xhtml=\"http://www.w3.org/1999/xhtml\" xmlns:xlink=\"http://www.w3.org/1999/xlink\" class=\"mainContent\">\n <!-- Created with Product Designer Tool by Riaxe-->\n <defs>\n  <mask patternUnits=\"userSpaceOnUse\" x=\"0\" y=\"0\" width=\"500\" height=\"500\">\n   <image id=\"xe_d8wi\" xlink:href=\"#\" x=\"0\" y=\"0\" width=\"500\" height=\"500\" xmlns:xlink=\"http://www.w3.org/1999/xlink\"/>\n  </mask>\n  <image id=\"xe_xcyq\" xlink:href=\"#\" width=\"500\" height=\"500\" preserveAspectRatio=\"none\" xmlns:xlink=\"http://www.w3.org/1999/xlink\"/>\n  <clipPath id=\"boundryClipPath0\" class=\"boundryClipPath\">\n   <rect aHeight=\"8.27\" aWidth=\"11.69\" height=\"196.20741\" width=\"138.80542\" y=\"185.27991\" x=\"178.72622\" id=\"boundRectangle\"/>\n  </clipPath>\n  <filter id=\"filter8483\" style=\"color-interpolation-filters:sRGB;\">\n   <feColorMatrix values=\"0\" result=\"colormatrix\" id=\"feColorMatrix8485\" type=\"matrix\"/>\n  </filter>\n  <g id=\"xe_8v6v\" type=\"patternG\" xmlns:xlink=\"http://www.w3.org/1999/xlink\"/>\n </defs>\n <g id=\"layer_background\">\n  <title>background</title>\n  <rect id=\"canvas_background\" x=\"-1\" y=\"-1\" width=\"502\" height=\"502\" fill-opacity=\"0\" stroke=\"#000000\" stroke-width=\"0\" fill=\"#fff\" opacity=\"0\"/>\n  <g id=\"bleedM\">\n   <rect isBleed=\"false\" id=\"cropM\" isbleed=\"false\" class=\"bleedRect\" width=\"0\" height=\"0\" x=\"0\" y=\"0\" fill=\"none\" stroke=\"#ff0000\" stroke-width=\"0.5\" display=\"none\"/>\n   <rect id=\"safeM\" class=\"bleedRect\" width=\"0\" height=\"0\" x=\"0\" y=\"0\" fill=\"none\" stroke=\"#2B8F49\" stroke-width=\"0.5\" stroke-dasharray=\"3,3\" display=\"none\"/>\n   <path isBleed=\"false\" pointer-events=\"bounding-box\" id=\"cropMMask\" isbleed=\"false\" class=\"bleedPath\" width=\"0\" height=\"0\" awidth=\"0\" aheight=\"0\" x=\"0\" y=\"0\" ax=\"0\" ay=\"0\" fill=\"none\" stroke=\"#ff0000\" display=\"none\"/>\n   <path pointer-events=\"bounding-box\" id=\"safeMMask\" class=\"bleedPath\" width=\"0\" height=\"0\" awidth=\"0\" aheight=\"0\" x=\"0\" y=\"0\" ax=\"0\" ay=\"0\" fill=\"none\" stroke=\"#2B8F49\" stroke-width=\"2\" stroke-dasharray=\"5,5\" display=\"none\"/>\n   <rect id=\"hAlignTleft\" class=\"bleedRect\" width=\"0\" height=\"0.5\" x=\"0\" y=\"0\" fill=\"#ff0000\" display=\"none\"/>\n   <rect id=\"hAlignBleft\" class=\"bleedRect\" width=\"0\" height=\"0.5\" x=\"0\" y=\"0\" fill=\"#ff0000\" display=\"none\"/>\n   <rect id=\"vAlignBleft\" class=\"bleedRect\" width=\"0.5\" height=\"0\" x=\"0\" y=\"0\" fill=\"#ff0000\" display=\"none\"/>\n   <rect id=\"vAlignTleft\" class=\"bleedRect\" width=\"0.5\" height=\"0\" x=\"0\" y=\"0\" fill=\"#ff0000\" display=\"none\"/>\n   <rect id=\"hAlignTright\" class=\"bleedRect\" width=\"0\" height=\"0.5\" x=\"0\" y=\"0\" fill=\"#ff0000\" display=\"none\"/>\n   <rect id=\"hAlignBright\" class=\"bleedRect\" width=\"0\" height=\"0.5\" x=\"0\" y=\"0\" fill=\"#ff0000\" display=\"none\"/>\n   <rect id=\"vAlignTright\" class=\"bleedRect\" width=\"0.5\" height=\"0\" x=\"0\" y=\"0\" fill=\"#ff0000\" display=\"none\"/>\n   <rect id=\"vAlignBright\" class=\"bleedRect\" width=\"0.5\" height=\"0\" x=\"0\" y=\"0\" fill=\"#ff0000\" display=\"none\"/>\n  </g>\n </g>\n <g id=\"layer_stage\" clip-path=\"url(#boundryClipPath0)\">\n  <title>stage</title>\n  <g id=\"background\" type=\"background\"/>\n  <g id=\"pbgpattern\" type=\"bgpattern\"/>\n  <g id=\"backgroundBorder\" type=\"bgBorder\"/>\n  <g xe_p=\"&amp;#35;&amp;#103;&amp;#81;&amp;#84;&amp;#19;&amp;#58;&amp;#122;&amp;#61;&amp;#93;&amp;#111;&amp;#91;&amp;#98;&amp;#97;&amp;#115;&amp;#26;&amp;#28;&amp;#19;&amp;#116;&amp;#33;&amp;#53;&amp;#93;&amp;#18;&amp;#11;&amp;#34;&amp;#60;&amp;#32;&amp;#75;&amp;#89;&amp;#86;&amp;#110;&amp;#122;&amp;#105;&amp;#26;&amp;#83;&amp;#94;&amp;#108;&amp;#55;&amp;#55;&amp;#75;&amp;#18;&amp;#11;&amp;#91;&amp;#122;&amp;#102;&amp;#125;&amp;#118;&amp;#114;&amp;#66;&amp;#109;&amp;#125;&amp;#26;&amp;#28;&amp;#19;&amp;#35;&amp;#105;&amp;#0;&amp;#15;&amp;#115;&amp;#9;&amp;#52;&amp;#122;&amp;#105;&amp;#26;&amp;#19;&amp;#114;&amp;#56;&amp;#106;&amp;#3;&amp;#12;&amp;#114;&amp;#19;&amp;#44;&amp;#122;&amp;#102;&amp;#124;&amp;#3;&amp;#116;&amp;#68;&amp;#30;&amp;#117;&amp;#26;&amp;#109;&amp;#29;&amp;#34;&amp;#40;&amp;#55;&amp;#81;&amp;#83;&amp;#84;&amp;#34;&amp;#98;&amp;#103;&amp;#8;&amp;#30;&amp;#1;&amp;#48;&amp;#122;&amp;#105;&amp;#26;&amp;#89;&amp;#66;&amp;#83;&amp;#59;&amp;#36;&amp;#84;&amp;#81;&amp;#83;&amp;#108;&amp;#61;&amp;#103;&amp;#2;&amp;#18;&amp;#0;&amp;#34;&amp;#116;&amp;#103;&amp;#91;&amp;#95;&amp;#93;&amp;#111;&amp;#42;&amp;#0;&amp;#92;&amp;#89;&amp;#69;&amp;#34;&amp;#98;&amp;#35;&amp;#89;&amp;#92;&amp;#66;&amp;#101;&amp;#116;&amp;#103;&amp;#74;&amp;#85;&amp;#66;&amp;#105;&amp;#34;&amp;#32;&amp;#26;&amp;#10;&amp;#87;&amp;#97;&amp;#52;&amp;#54;&amp;#93;&amp;#28;&amp;#19;&amp;#112;&amp;#55;&amp;#54;&amp;#81;&amp;#68;&amp;#88;&amp;#111;&amp;#54;&amp;#103;&amp;#2;&amp;#86;&amp;#80;&amp;#108;&amp;#43;&amp;#32;&amp;#20;&amp;#18;&amp;#93;&amp;#111;&amp;#59;&amp;#46;&amp;#104;&amp;#66;&amp;#94;&amp;#112;&amp;#61;&amp;#55;&amp;#76;&amp;#89;&amp;#84;&amp;#115;&amp;#122;&amp;#127;&amp;#67;&amp;#18;&amp;#82;&amp;#111;&amp;#52;&amp;#42;&amp;#74;&amp;#117;&amp;#85;&amp;#105;&amp;#44;&amp;#103;&amp;#2;&amp;#86;&amp;#80;&amp;#108;&amp;#43;&amp;#32;&amp;#20;&amp;#18;&amp;#67;&amp;#101;&amp;#43;&amp;#44;&amp;#66;&amp;#85;&amp;#19;&amp;#58;&amp;#62;&amp;#36;&amp;#84;&amp;#67;&amp;#84;&amp;#44;&amp;#122;&amp;#40;&amp;#87;&amp;#70;&amp;#84;&amp;#34;&amp;#98;&amp;#35;&amp;#89;&amp;#92;&amp;#66;&amp;#101;&amp;#116;&amp;#103;&amp;#74;&amp;#95;&amp;#69;&amp;#97;&amp;#44;&amp;#32;&amp;#26;&amp;#10;&amp;#87;&amp;#97;&amp;#52;&amp;#54;&amp;#93;&amp;#28;&amp;#19;&amp;#100;&amp;#61;&amp;#41;&amp;#93;&amp;#68;&amp;#84;&amp;#34;&amp;#98;&amp;#35;&amp;#89;&amp;#92;&amp;#66;&amp;#101;&amp;#37;&amp;#56;\" scaled=\"true\" id=\"xe_jb96\">\n   <g id=\"xe_9d7t\">\n    <g id=\"xe_glae\">\n     <path id=\"xe_gfym\" pointer-events=\"bounding-box\" d=\"M310.59136335441656,288.63004089439437 L265.97926862976146,298.04642533153816 C266.1661972210724,297.0758492715411 266.33057205596754,296.0815726539545 266.472010867389,295.06321321172044 C266.4968582261522,294.87552008629365 266.52170558491537,294.68973829615635 266.5461706766207,294.50739690954015 C266.58592645064186,294.1862925809078 266.6252999576051,293.86251238287014 266.66505573162624,293.5364385824852 C266.669642936321,293.4970650755219 266.67461240807364,293.45730930150074 266.6795818798263,293.41755352747964 C266.72927659735274,292.9530990521364 266.775913178416,292.48635097444577 266.8202561571319,292.0169270273499 C266.8301951006372,291.88351582414435 266.84051631120036,291.7501046209387 266.85007298764776,291.61669341773313 C266.86803953936885,291.40874013823793 266.88562382403205,291.199640057569 266.9016790404637,290.9905399769001 L310.5061178005059,285.6395657004766 L310.59136335441656,288.63004089439437 zM310.3730888643582,280.80771008867544 L266.5465529436786,275.24916479981465 C266.5442593413312,275.2277578445725 266.54158347192595,275.20711542344617 266.5389076025207,275.18609073526187 C266.4991518284995,274.8898337653927 266.4574847191889,274.59548813081307 266.4127594734151,274.3038183656387 C266.2992261572201,273.52322903341576 266.17307802811456,272.75984171879816 266.0350796202142,272.0140386888437 C265.9559503392298,271.598896663969 265.87452745589803,271.19139998025224 265.79004643610307,270.79116637063544 C265.68645206341336,270.3125680141501 265.5771236848552,269.83970366353316 265.4639726357181,269.3718087846689 L310.2947241174896,278.04659512949513 L310.3730888643582,280.80771008867544 zM186.7930298537333,253.2340226685457 L235.76335130545687,262.9910070542745 C234.7465209314544,264.6217583232574 233.89330085823127,266.5499133632831 233.20254428461385,268.77547217435165 C233.1780791929085,268.8595709270887 233.15055596474002,268.9459632821731 233.12112140128207,269.0350315066628 C232.94336721936057,269.627927713459 232.7751697138865,270.2403195402078 232.6169111519177,270.873353788083 C232.61117714604924,270.89667207861464 232.6050608731229,270.9199903691463 232.5985623331387,270.9436909267358 L186.33010444662165,265.07359798569007 L186.49677288386414,253.19694276392983 L186.7930298537333,253.27110257316156 L186.7930298537333,253.2340226685457 zM185.83315727135727,300.94018695980833 L232.2541397139747,295.2409673936419 C232.5786844461281,297.1981747300677 232.98847473219226,299.0192949938826 233.48427510628295,300.70318138391303 C233.4892445780356,300.7180897991709 233.49421404978824,300.7352918167762 233.49918352154089,300.7551697037868 C233.78550154790472,301.7242166955523 234.10010733655284,302.64815617448613 234.44414768865894,303.5269881405883 L185.66648883411477,312.8577447567634 L185.83315727135727,300.94018695980833 z\" fill=\"#EFCB58\" clip-rule=\"evenodd\" fill-rule=\"evenodd\"/>\n     <path id=\"xe_24tb\" pointer-events=\"bounding-box\" d=\"M238.45718726244758,259.6817211340718 C239.6628575630505,258.5700885297112 241.01417161271166,257.73024780351443 242.51112941143106,257.1618166884236 C242.57038080540488,257.1373515967183 242.63230806878397,257.11518010736035 242.69652893451047,257.09530222034977 C242.7114373497684,257.08995048153923 242.73093296972104,257.0826874074392 242.75578032848426,257.0727484639339 C242.85440522942136,257.0379621616654 242.95570599976372,257.0035581264548 243.05968263951132,256.96915409124415 L248.8923134088833,256.31700649047417 C249.67290274110627,256.2478161529951 250.399210151108,256.18856475902123 251.0712356388886,256.1388700414948 C251.27383717957326,256.1243438932948 251.47108698144746,256.1121113474421 251.66374957862683,256.10179013687895 C252.71154358431886,256.03756927115245 253.6056662327368,256.00813470769447 254.3472643250544,256.01310417944717 C254.4852627329547,256.01310417944717 254.6190562032182,256.01578004885243 254.74749793467115,256.020749520605 C255.31057731095146,256.0303061970524 255.7727381839473,256.0677683687262 256.13321601954294,256.1319892344527 C256.28612284270116,256.15645432615804 256.4199163129647,256.1862711566739 256.5334496291597,256.2206751918845 C256.8147981837709,256.2206751918845 257.0942354030926,256.25010975534246 257.3709967530091,256.30936114931626 C258.5021249773223,256.54636672521156 259.5965555640776,257.2707627999239 260.653906246217,258.48102030522153 C261.89933232084104,259.9042005617671 263.0056131863911,261.90269274044556 263.9742779110987,264.47687910831496 C263.99453806516715,264.5265738258414 264.01174008277246,264.57321040690465 264.0266484980304,264.61755338562057 C264.25371513042046,265.2307097464852 264.4685492169578,265.858009988492 264.6711507576425,266.5002186457567 C264.92344701585364,267.305273069685 265.1558653870542,268.13326351708696 265.3680236041863,268.983043186789 C265.5163432226498,269.57593939358514 265.6573997670133,270.1787745438866 265.79004643610307,270.79116637063544 C265.87452745589803,271.19139998025224 265.9559503392298,271.598896663969 266.0350796202142,272.0140386888437 C266.17307802811456,272.75984171879816 266.2992261572201,273.52322903341576 266.4127594734151,274.3038183656387 C266.4574847191889,274.59548813081307 266.49953409555746,274.88945149833484 266.5389076025207,275.18609073526187 C266.68225774923155,276.31760122663303 266.8007605371792,277.48122215086744 266.8944159663637,278.67695350796504 C266.90932438162156,278.8791727815919 266.92423279687955,279.08215658933443 266.93914121213743,279.28475813001916 C266.959019099148,279.571076156383 266.9788969861586,279.86045231921 266.9980103390534,280.15173981732653 C267.0079492825587,280.3646625685744 267.01827049312186,280.5791143880539 267.02782716956926,280.79700661105437 C267.0721701482851,281.7607018640093 267.1016047117431,282.7435104698591 267.11651312700104,283.7465792297773 C267.1218648658116,283.9984932209305 267.12415846815895,284.2504072120838 267.12415846815895,284.50270347029493 C267.12415846815895,284.63114520174787 267.12415846815895,284.7595869332008 267.12415846815895,284.88841093171163 C267.12415846815895,285.15026386637015 267.12415846815895,285.41441040337605 267.12415846815895,285.6812328097872 C267.1191889964063,285.8245829564981 267.11651312700104,285.97022670555634 267.11651312700104,286.11854632401986 C267.10695645055364,286.8448537340216 267.0897544329483,287.56389806992337 267.0649070741851,288.2752970646672 C267.0545858636219,288.40909053493067 267.0477050565798,288.54479534048363 267.04235331776925,288.682793748384 C266.9976280719955,289.68089303654955 266.933407206269,290.65949670476243 266.8496907205899,291.61784021890685 C266.8401340441425,291.75125142211243 266.8298128335793,291.884662625318 266.819873890074,292.0180738285236 C266.7755309113581,292.4878800426774 266.72889433029485,292.95424585331006 266.6791996127684,293.4187003286533 C266.67423014101576,293.45845610267446 266.6692606692631,293.49821187669556 266.66467346456835,293.53758538365884 C266.6249176905472,293.86404145110174 266.585544183584,294.1874393820815 266.5457884095628,294.5085437107138 C266.5213233178575,294.69126736438795 266.49647595909425,294.87666688746737 266.4716286003311,295.0643600128941 C266.27896600315165,296.45275396717113 266.0442540296037,297.7964226756744 265.7674926796873,299.0961306725196 C265.74302758798194,299.20469451696204 265.7181802292187,299.31593423080966 265.6933328704555,299.42946754700466 C265.55533446255515,300.0521805843167 265.40701484409163,300.6626610757761 265.2491385491807,301.260144487267 C265.23881733861754,301.29990026128814 265.22887839511225,301.33927376825136 265.2193217186649,301.3790295422725 C265.0515064802487,302.0162687277846 264.8710764289219,302.641275367444 264.6780315646846,303.25404946125076 C264.6340708530266,303.38746066445634 264.5916392096002,303.52048960060404 264.55226570263693,303.6539008038096 C264.38483273127866,304.16804999667926 264.20937215170454,304.6718779789858 264.0262662309725,305.16614928484483 C264.0113578157146,305.21049226356075 263.99415579810926,305.2575111116819 263.9738956440408,305.30682356215044 C263.8951486301143,305.5239512510352 263.8133434797246,305.7364917352252 263.7296269940455,305.94406274766254 C263.6554671848137,306.1271686683945 263.58360097792934,306.30454058325813 263.51441064045025,306.4777075604849 C263.2674661210496,307.0602825567178 263.0124939934332,307.6088357847981 262.7506410587747,308.1229849776678 C262.7162370235641,308.1872058433942 262.6841265907008,308.254102578526 262.6546920272429,308.3229106489472 C262.2743363046367,309.0442485871963 261.8790721667726,309.69907205737155 261.46851734659265,310.2869987924151 C261.2812064882238,310.5488517270736 261.09083749339175,310.7957962464742 260.8981748962123,311.0278323506169 C260.81904561522794,311.12683951861186 260.7376227318962,311.22317081720155 260.6531417121012,311.3172085134439 C260.0701844488103,311.98388226241394 259.47728824201414,312.5030009270363 258.8748353587706,312.87341770613716 C258.4596933338959,313.1253316972904 258.0422577066738,313.30843761802237 257.6221462100465,313.4219709342174 C257.2616683744509,313.5209781022124 256.89851466945004,313.57029055268094 256.5326850950439,313.57029055268094 C256.2513365404327,313.57029055268094 255.96922345170566,313.54085598922296 255.68787489709447,313.48160459524917 L255.68787489709447,313.57029055268094 L241.1246467924435,312.3844981390886 C240.70988703462672,312.2312090488724 240.19306197235176,311.89787217438743 239.5757006738503,311.38372298151774 C239.53135769513437,311.3493189463071 239.48892605170795,311.31453264403865 239.4495525447447,311.280128608828 C239.3360192285497,311.18112144083307 239.22477951470205,311.08249653989594 239.1158334032018,310.98387163895893 C238.57721911862683,310.4899826001577 238.06345219281505,309.9242273544721 237.5741503587086,309.2869881689601 C237.08523079166005,308.6547184552006 236.6158068445642,307.94790666515155 236.165878517421,307.16731733292863 C235.89905611100983,306.7028628575854 235.64217264810395,306.2189127622895 235.39484586164545,305.7147025129251 C235.34553341117692,305.61569534493015 235.29851456305573,305.5166881769352 235.25417158433984,305.418445543056 C234.58214609655928,304.0002347582631 233.99651296386313,302.4467014349751 233.49765445330928,300.7566987720184 C233.49268498155664,300.73682088500783 233.487715509804,300.7196188674025 233.48274603805135,300.7047104521446 C232.98388752749753,299.0097383174352 232.5710391049702,297.1767677748255 232.2449653045852,295.20541655725765 C232.23005688932727,295.1067916563205 232.21553074112722,295.00778448832557 232.2006223258693,294.9091595873885 C231.80038871625254,292.39919408524554 231.53624217924664,289.67171862716003 231.40741818073582,286.72711548018975 C231.39786150428841,286.5593002417736 231.3902161631305,286.39377860570477 231.38524669137786,286.2305505719833 C231.33593424090932,284.89643853992743 231.31338048449348,283.5179835291557 231.318732223304,282.095185539668 C231.318732223304,282.07072044796274 231.318732223304,282.0481666915469 231.318732223304,282.0282888045363 C231.318732223304,281.93960284710454 231.318732223304,281.8528282249622 231.318732223304,281.76911173928306 C231.29885433629346,280.9040413872652 231.3386101103146,279.8000541240625 231.4372350112517,278.4560031485014 C231.4372350112517,278.4510336767487 231.4372350112517,278.44644647205394 231.4372350112517,278.4410947332434 C231.44220448300433,278.3623477193169 231.44984982416224,278.2858943077378 231.45940650060962,278.21135223144813 C231.6620080412943,275.61728797656815 232.04771550271104,273.17154334015174 232.6153820836861,270.87450058925674 C232.7736406456549,270.2418486084394 232.941838151129,269.62907451463263 233.11959233305046,269.0361783078365 C233.14902689650845,268.94749235040473 233.17616785761902,268.8607177282624 233.20101521638225,268.77661897552537 C233.90782700643132,266.499071844583 234.78474763724398,264.53230783170983 235.83215937587806,262.87709147102163 C235.88644129809927,262.78840551358985 235.94339908972572,262.69895502204224 236.00265048369954,262.61026906461046 C236.605485634001,261.6863295856766 237.26260270652364,260.86407314414305 237.97400170126747,260.1423529388361 C238.13378933146785,259.98332984275146 238.294341495784,259.8300407525353 238.45718726244758,259.6817211340718 zM238.7461811582167,265.6771976701073 C238.80543255219055,265.4944740164332 238.86239034381697,265.32398290861175 238.91667226603818,265.16610661370083 C238.9315806812961,265.1164118961744 238.94648909655405,265.0670994457058 238.96101524475407,265.0177869952373 L240.3841955012996,269.4941342431955 L240.61393800309492,269.4199744339637 L239.75421938988757,272.7181746094875 C239.74428044638228,272.7625175882034 239.734341502877,272.80953643632455 239.7244025593717,272.8588488867931 C239.70452467236112,272.94294763953013 239.68464678535054,273.0366030687146 239.66515116539787,273.1405797084622 L237.93080552372527,269.5533856371693 L237.64181162795614,269.6940599144749 L237.64181162795614,269.68641457331705 C237.67659793022466,269.5380949548535 237.7060324936826,269.40735962105316 237.73087985244584,269.29382630485816 C237.95335928014111,268.43410769165087 238.1211745185573,267.8041315802388 238.2347078347523,267.40389797062204 L238.7461811582167,265.6771976701073 zM238.12385038796256,260.3193425866417 L238.02751908937284,260.215748213952 L238.02751908937284,260.36406783241557 L238.07950740924667,260.73448461151645 C238.14372827497314,261.0655278836541 238.25496798882077,261.4091859687023 238.41322655078957,261.7646943325452 C238.5860112609584,262.14505005515144 238.7714107840378,262.45889130968374 238.9690428529699,262.7058358290844 L239.2136937700231,262.99521199191133 L239.250773674639,263.0322918965272 C239.11736247143338,263.3285488663964 238.98165766588042,263.645065990334 238.8432769909222,263.98069646716635 C238.77408665344308,264.1534811773352 238.70757218536926,264.3239722851567 238.64335131964276,264.4921697906308 C238.59403886917423,264.6156420503311 238.54702002105307,264.73911431003137 238.50229477527927,264.8629688367896 C238.19609886190483,265.6435581690125 237.9441848707516,266.3205531285457 237.74617053476166,266.89357144833133 L236.18996134206841,263.765862380629 L237.46443971309256,267.73876391333863 C237.35587586865017,268.05489877021836 237.2052626478393,268.50712069970893 237.01221778360198,269.0950474347524 L236.72322388783286,270.0954403252654 C236.66397249385903,270.28313345069216 236.6119841739852,270.4608876326136 236.56764119526935,270.6290851380877 C236.53323716005872,270.752557397788 236.50342032954285,270.86876658338826 236.47895523783754,270.9773304278307 C236.4640468225796,271.0319946171097 236.44913840732167,271.0862765393309 236.43422999206376,271.14055846155213 L236.4120585027058,271.25179817539976 L234.12189655885288,267.79839757437037 L236.18957907501053,272.1042537145071 L235.88567676398347,273.2973092021994 C235.76220450428318,273.7965499798112 235.60165233996702,274.56261316383404 235.40402027103494,275.59511648721025 C235.35967729231905,275.84206100661083 235.3176279159505,276.0840360542588 235.27787214192938,276.321423897212 L232.82486443141292,272.6229901120715 L235.09285488590785,277.3512513511829 L235.10776330116582,277.343606010025 C234.9842910414655,278.1043174552374 234.88528387347054,278.7889577559285 234.81150633129667,279.39676237798255 C234.79659791603873,279.50532622242497 234.7816895007808,279.6138900668673 234.76678108552287,279.7228361783676 C234.7373465220649,279.9747501695208 234.7124991633017,280.2117557454161 234.6926212762911,280.4342351731114 L234.5890269036014,281.6941873959355 L232.26943039629052,278.1960615491323 L234.4926956050117,282.8283737567119 L234.47778718975374,282.9468765446596 C234.47778718975374,282.9617849599175 234.47778718975374,282.9816628469281 234.47778718975374,283.0061279386334 C234.47281771800112,283.03556250209135 234.47014184859586,283.07302467376513 234.47014184859586,283.11736765248105 C234.45026396158528,283.4977233750872 234.41815352872203,284.2859580484681 234.37381055000614,285.4816894055657 C234.36387160650085,285.75845075548216 234.36387160650085,286.1682410415463 234.37381055000614,286.71182479787393 L232.13563692602705,283.3322017390184 L234.410890454622,288.06849058634566 L234.4479703592379,289.290980637496 C234.46784824624848,289.56774198741243 234.4923133379538,289.9851776146345 234.52213016846966,290.54366978622005 C234.55653420368026,290.82501834083126 234.59399637535404,291.24016036570595 234.63336988231728,291.7887135937862 C234.63833935406993,291.84299551600736 234.64330882582257,291.89727743822857 234.64827829757522,291.95194162750767 L232.00260798987935,289.42477410775945 L234.76678108552287,292.93016302866266 C234.76678108552287,292.95462812036794 234.76907468787024,292.9821513485365 234.7744264266808,293.0119681790523 L235.7602931689937,298.3629424554758 L232.97356631693435,296.1691118102126 L236.00456181898903,299.3266377084307 C236.0936300434787,299.6676199240737 236.14294249394726,299.8553130495004 236.15288143745255,299.88971708471104 L236.75342298540662,301.9207019633107 L237.35358226630282,303.60305928510945 L234.2705984443743,301.1871314792089 L237.49463881066632,304.5369377075486 L237.65022150322983,304.37370967382714 C237.73432025596688,304.58128068626445 237.84059049806189,304.8435158879809 237.96864996245694,305.1596507448606 C238.00840573647807,305.2586579128556 238.05274871519396,305.3645458878927 238.10206116566252,305.4784614711456 L238.43578030720542,306.24911185986326 C238.5542830951531,306.54536882973235 238.66322920665334,306.7900197467856 238.7618541075904,306.98306461102294 L239.3918302190025,308.27245139730496 C239.6636220971663,308.80112673837465 239.8390826767404,309.1398153516702 239.9178296906669,309.28775270307585 C239.93273810592484,309.3221567382865 239.9449706517775,309.34700409704965 239.95490959528277,309.3615302452497 L241.11126744541716,311.3626982933335 L240.8593534542639,310.81414506525323 C240.82953662374806,310.7445724607162 240.8001020602901,310.67844025970027 240.77028522977423,310.61421939397377 C240.56271421733686,310.13485650337265 240.36278854605746,309.69257351738736 240.17012594887802,309.28737043601797 C240.16515647712538,309.2774314925127 240.16018700537273,309.2674925490074 240.1552175336201,309.25793587256 C240.11546175959896,309.18377606332825 239.95987906703542,308.81068341482205 239.6880871888716,308.1386579270415 L239.14717930194922,306.81180896908563 C239.06805002096485,306.6287030483536 238.98662713763306,306.4020186830215 238.90252838489602,306.1298445377998 L243.57880130413366,308.8722284111433 L243.6900410179813,308.68721115512176 C243.69501048973393,308.69676783156916 243.6995976944287,308.70708904213234 243.70494943323922,308.71664571857974 C243.74470520726035,308.7957749995641 243.85059318229744,308.9857617273383 244.02337789246627,309.28737043601797 C244.1025071734507,309.4356900544815 244.1988384720404,309.6111506340556 244.3123717882354,309.8137521747403 C244.38156212571454,309.9368421673827 244.45572193494627,310.07331150705147 244.5348512159307,310.22124885845705 L244.82384511169982,310.73960298896355 L243.8383606364448,308.664275131648 C243.82842169293951,308.64439724463745 243.80854380592893,308.59776066357415 243.77910924247095,308.5236008543424 L243.8012807318289,308.4865209497266 L243.7492924119551,308.45670411921066 C243.66519365921806,308.2690109937839 243.53216472307037,307.9628150804095 243.34905880233833,307.5381163790874 L242.80050557425807,306.2189127622895 C242.73131523677895,306.06562367207334 242.63498393818924,305.8209727550201 242.51151167848894,305.48496001112983 L242.22978085681984,304.69940120715427 C242.1013391253669,304.3389233715586 242.00271422442984,304.0617797545843 241.93352388695072,303.86911715740484 C241.8100516272504,303.52813494176195 241.7137203286607,303.23455384129807 241.6445299911816,302.98722705483954 L241.05889685848544,301.1194702099614 L240.54016046092102,299.0961306725196 C240.4908480104525,298.93787211055087 240.41171872946808,298.58236374670787 240.30315488502572,298.02884104687496 L240.06576704207254,296.9321168577723 C240.02601126805138,296.7490109370403 239.97708108464073,296.4944210764818 239.91744742360902,296.16872954315465 C239.89756953659844,296.0601656987123 239.87539804724048,295.94128064370676 239.85093295553514,295.8128389122538 L239.3543680473287,292.3001869172506 C239.334872427376,292.18130186224505 239.29511665335485,291.7787746502809 239.23586525938106,291.0922230143003 L239.13227088669132,289.8693506960921 C239.107805794986,289.3162102633171 239.08525203857016,288.9037441078477 239.06575641861747,288.6315699626259 L239.00650502464364,286.13421927339357 C239.00650502464364,285.44231589860243 239.0114744963963,285.0248802713804 239.02141343990158,284.8819123917274 C239.02141343990158,284.7829052237324 239.02370704224896,284.68657392514274 239.02867651400157,284.59253622890037 C239.02867651400157,284.5481932501845 239.03097011634895,284.506143873816 239.03632185515949,284.46677036685276 C239.06078694686482,283.44382371992396 239.08334070328067,282.7500090098433 239.10283632323336,282.38417943543715 L239.29549892041277,279.90173716146273 C239.31996401211808,279.57528109401983 239.36468925789188,279.1704602797083 239.42891012361832,278.68612791735455 C239.49810046109747,278.1475136327796 239.547412911566,277.74460415375756 239.57722974208184,277.47816401440423 L239.7400755087454,276.284726259654 C239.8142353179772,275.76102039033697 239.87845618370363,275.3707257242255 239.93273810592484,275.1138422613196 C240.086027196141,274.23959749991224 240.20452998408865,273.5970065755896 240.28862873682567,273.18721628952545 C240.3134760955889,273.0438661428146 240.33564758494686,272.9299505595617 240.35552547195744,272.8458518068246 L240.82227354964803,270.6818379920773 C241.04972244909595,269.7678374566488 241.21524408516478,269.0908424971156 241.3188384578545,268.6512353805356 C241.47174528101277,268.08280426544474 241.60286288187098,267.6160561877541 241.71142672631333,267.250226613348 C241.7607391767819,267.0724724314265 241.80546442255567,266.9195656082682 241.84483792951892,266.7907416097574 C241.84483792951892,266.77621546155734 241.8471315318663,266.7639829157047 241.85210100361894,266.7536617051415 L242.37810047528336,265.0265791375689 C242.50157273498365,264.66113183022065 242.60822524413655,264.34729057568836 242.69691120156835,264.0854376410298 C242.77604048255273,263.8384931216292 242.84026134827923,263.63818518329185 242.88957379874776,263.48527836013363 C242.9193906292636,263.40117960739656 242.94882519272159,263.3220503264122 242.97864202323746,263.24827278423834 C243.2748989931066,262.39352364278363 243.54936674067568,261.64236887401864 243.8012807318289,260.99480847794337 L244.70534232375215,258.86825683486984 L244.41634842798305,259.40190164769217 C244.12467866280866,259.984858910983 243.87505827400275,260.4986258367948 243.66786952862333,260.9432024251275 C243.46526798793863,261.3931307522707 243.16404154631687,262.1018538776092 242.7638079367001,263.0701363352589 C242.7194649579842,263.1691435032539 242.67512197926828,263.2727378759436 242.63039673349448,263.381301720386 C242.56617586776804,263.5491169588022 242.50424860438892,263.714638594871 242.44499721041512,263.87786662859247 C242.25730408498833,264.35722951919365 242.0917824489195,264.79416076636835 241.94843230220863,265.18980717129034 L240.7549945474584,261.76584113371894 L240.3325894484837,261.91416075218245 L241.62197623476575,265.59768612206506 L241.8295472472031,265.52390857989116 C241.69116657224487,265.9042643024974 241.5749573866446,266.24027704638763 241.48130195746018,266.531946811562 C241.4663935422022,266.56635084677265 241.45416099634957,266.60113714904116 241.44422205284428,266.63554118425174 C241.42931363758635,266.674914691215 241.39223373297045,266.78615440506263 241.33298233899666,266.9688780587368 C241.23435743805953,267.2750739721112 241.0734230066855,267.78922316498085 240.8513258460481,268.5101788361721 L240.73282305810045,268.97730918092054 L239.33181429091286,264.5529502528362 L239.09480871501754,264.6267277950101 C239.15406010899136,264.429095726078 239.20337255945992,264.26395635706706 239.24312833348105,264.1301628868036 C239.61354511258196,263.0579037894063 239.88036751899313,262.3048376853518 240.04359555271458,261.86981777346654 C240.07341238323045,261.7757800772242 240.1001710772831,261.6970330632977 240.12501843604633,261.63281219757124 L240.98473704925368,259.483324531024 L240.68848007938453,260.02461468500417 C240.51034363040517,260.3506884853892 240.33985252258373,260.68173175752685 240.17700675592016,261.01774450141716 C240.08832079848838,261.19052921158595 240.00154617634604,261.3659897911601 239.91744742360902,261.5437439730815 C239.89298233190368,261.5984081623606 239.86813497314046,261.6526900845818 239.84328761437723,261.70697200680297 C239.67547237596105,262.06286263770386 239.50001179638696,262.4531573038153 239.3172881427128,262.8778560051374 C239.31231867096017,262.8036961959057 239.29741025570223,262.7023954255633 239.27294516399692,262.5739536941104 C239.20872429827045,262.24291042197274 239.09251511267018,261.8992523369245 238.92469987425397,261.5437439730815 C238.77638025579046,261.2027617574386 238.59098073271105,260.88930276996416 238.36888357207368,260.6026024765424 C238.28937202403137,260.4921272968106 238.2079491406996,260.39808960056826 238.12385038796256,260.3193425866417 zM241.77029585322924,258.20693482471034 L243.00769431963752,261.5490957118921 L243.4228363445122,261.39351301932857 L242.18505561104604,258.0513521321468 L241.77029585322924,258.20693482471034 zM246.2688145905454,260.3193425866417 C246.2244716118295,260.4229369593315 246.17745276370835,260.5318830708317 246.12814031323978,260.6454163870268 C245.8811957938392,261.208878030365 245.58226295456478,261.9176011557035 245.23134179541657,262.7723502971582 C244.96948886075808,263.43940631318617 244.74700943306277,264.02733304822965 244.56428577938865,264.53613050228876 C244.44578299144098,264.8522653591685 244.34180635169338,265.13628978318496 244.2531203942616,265.3882037743382 C244.17399111327717,265.6202398784809 244.10480077579808,265.8278108909182 244.04554938182423,266.01091681165025 C244.0306409665663,266.0552597903661 243.8307152952869,266.6829422994308 243.44539010092805,267.89358207178634 L242.3559289859254,272.09546157217545 C242.28673864844632,272.3722229220919 242.17817480400393,272.895928791409 242.0298551855404,273.66657918012663 C242.00042062208246,273.81489879859015 241.96792792216132,273.97315736055896 241.93352388695072,274.14097259897517 C241.91861547169276,274.214750141149 241.90408932349277,274.2938794221334 241.88918090823483,274.37797817487046 C241.8647158165295,274.4865420193128 241.7951432119925,274.87951255482955 241.68160989579746,275.5565075143628 C241.55813763609717,276.3221884313278 241.4939167703707,276.7250979103498 241.48894729861806,276.7644714173131 C241.291315229686,278.33520675820637 241.19001445934367,279.153258262103 241.18504498759103,279.2174791278295 L240.97747397515366,281.72247515821977 C240.972504503401,281.8016044392042 240.96753503164837,281.9250766989045 240.96256555989572,282.0932742043786 C240.9381004681904,282.5179729057007 240.90828363767457,283.23701724160236 240.87349733540606,284.25002494502587 C240.8685278636534,284.3536193177156 240.86623426130603,284.6208239911847 240.86623426130603,285.0504921642594 C240.86623426130603,285.0952174100332 240.86623426130603,285.1395603887491 240.86623426130603,285.1842856345229 C240.86623426130603,285.2878800072126 240.86623426130603,285.3995019881181 240.86623426130603,285.5176225090079 L240.9403940705378,288.0447900287561 C240.94536354229044,288.08454580277726 240.9476571446378,288.1262129120879 240.9476571446378,288.17093815786166 C240.96256555989572,288.38347864205167 240.97976757750104,288.66215132725756 240.99964546451162,289.00810301465316 C241.00461493626426,289.09678897208494 241.0095844080169,289.1931202706747 241.01455387976955,289.2970969104223 C241.04398844322753,289.5788277320914 241.08106834784337,289.9912938875608 241.12579359361717,290.53449537683053 C241.17510604408574,291.02876668268965 241.2221248922069,291.4362633664064 241.26685013798067,291.75736769503874 L241.9411692281086,295.8858519203119 C241.94613869986125,295.9057298073225 241.9511081716139,295.92751902962254 241.95607764336654,295.9523663883857 C241.97595553037712,296.0712514433913 242.01303543499301,296.2340972100548 242.0673173572142,296.4416682224922 L242.3341397636254,297.54603775275274 C242.45761202332568,298.094590980833 242.54668024781535,298.450099344676 242.60096217003655,298.6129451113395 L243.25310977080653,300.8289472459607 L243.8387429035027,302.51130456775945 C243.9178721844871,302.75824908716004 244.02643602892945,303.0499188523345 244.16481670388768,303.38593159622474 C244.23897651311944,303.5736247216515 244.35021622696706,303.84541659981534 244.49853584543058,304.2013072307162 L244.8246096458156,304.9792206935339 C244.8345485893209,304.99909858054446 244.84448753282618,305.02127006990236 244.85442647633147,305.04611742866564 C244.95802084902118,305.3079703633241 245.0520585452635,305.52777392161414 245.13615729800057,305.70591037059353 L245.7588703353126,307.0102055721335 C246.07003572043965,307.6378880811982 246.2527593741138,308.00104178619904 246.3074235633929,308.09966668713616 C246.31736250689815,308.11457510239404 246.32462558099817,308.129483517652 246.32959505275082,308.1443919329099 L246.17401236018728,307.9884269732885 L246.01078432646582,308.15891808110996 L246.32194971159288,308.47008346623704 L246.44045249954056,308.3511984112315 C246.57883317449878,308.60846414119527 246.74932428232023,308.9123664522223 246.95192582300496,309.2629053443126 C246.95192582300496,309.26825708312316 246.95421942535233,309.2751378901653 246.95957116416287,309.2854591007285 C247.0188225581367,309.3844662687235 247.07807395211051,309.4880606414132 247.13732534608434,309.59662448585556 L247.42631924185346,310.1302692986779 L246.44045249954056,308.0404152931623 L246.44045249954056,308.0327699520044 L246.60368053326198,308.18835264456794 L249.15301954236816,305.53503699571417 C249.28643074557374,305.83626343733596 249.37282310065814,306.02663243216796 249.4121966076214,306.1057617131524 L250.04217271903346,307.4027938405924 C250.13124094352315,307.57060907900853 250.24248065737078,307.78314956319855 250.37589186057636,308.0404152931623 L250.32428580776048,308.1141928353362 L250.45005166980815,308.18835264456794 C250.49936412027665,308.28200807375237 250.55135244015048,308.3833088440947 250.60601662942958,308.49225495559494 L251.76199221250602,310.50068607777877 L250.80594230070898,308.38866058290523 C250.80097282895633,308.3833088440947 250.7963856242616,308.37375216764735 250.79103388545104,308.35884375238936 L252.31780851468633,305.11301416379735 L250.54638296839784,307.78085596085117 C250.487131574424,307.63253634238765 250.4179412369449,307.4620452345662 250.3388119559605,307.26938263738674 L249.7979040690381,305.9352706053309 C249.7680872385223,305.8710497396045 249.6767254116852,305.6290746919565 249.52343632146903,305.2093454623871 L249.24935084095787,304.41614131725356 C249.22488574925254,304.3469509797744 249.2023319928367,304.282730114048 249.18283637288403,304.2234787200741 C249.08382920488904,303.9516868419103 249.0073757933099,303.73723502243087 248.95309387108873,303.57859419340423 C248.94315492758344,303.54380789113566 248.9305401146729,303.50940385592503 248.91601396647286,303.4749998207144 L250.58346287301373,300.12481132531684 L248.7084429540355,302.80029846352863 C248.6988862775881,302.765894428318 248.68894733408283,302.73378399545476 248.67900839057754,302.7039671649389 L247.61171876493285,298.80598997557684 C247.59184087792227,298.75132578629774 247.5624063144643,298.6328229983501 247.52303280750107,298.450099344676 L249.56089849314282,294.98140806133074 L247.36745011493753,297.7016204453163 L247.15223376134227,296.6565023090295 C247.14726428958963,296.63203721732424 247.14229481783698,296.60222038680837 247.13732534608434,296.56781635159774 C247.0975695720632,296.3847104308657 247.03602457574198,296.03914101052806 246.95192582300496,295.53034355646895 L246.76690856698343,294.3888941215925 C246.7175961165149,294.12207171518133 246.68548568365168,293.9294091180019 246.67057726839374,293.81090633005425 L246.5520744804461,292.8399480029993 L249.04216209557842,290.06812956619785 L246.47791467121434,292.1878004022293 L246.45574318185638,292.03221770966576 C246.45574318185638,292.0077526179604 246.4186632772405,291.6048431389384 246.34450346800872,290.82425380671543 L246.240909095319,289.60864456260725 C246.23593962356637,289.52454580987023 246.2332637541611,289.4454165288858 246.2332637541611,289.37163898671196 C246.21338586715052,288.9366190748267 246.1961838495452,288.60328220034165 246.1812754342873,288.371246096199 L246.16522021785568,287.54822512054966 L248.78871903619358,284.6208239911847 L246.14266646143983,286.8219177105479 L246.12049497208187,285.8807762140088 C246.12049497208187,285.1938423109703 246.12278857442925,284.7787002860956 246.12814031323978,284.6357324064426 C246.13310978499243,284.4331308657579 246.13807925674507,284.25002494502587 246.14304872849772,284.0867969113044 C246.14801820025036,283.88457763767764 246.152987672003,283.7091170581035 246.15795714375565,283.56079743964 C246.1629266155083,283.50154604566615 246.16560248491356,283.44458825403973 246.16560248491356,283.3903063318186 C246.17515916136097,283.12845339716 246.18509810486626,282.88877195185944 246.19503704837155,282.6712619959168 L248.67059851530382,279.9143519743733 L246.24702536824535,281.9155200224571 L246.61744214734625,277.8910124369316 L248.90760409119915,275.3344103537254 L246.69160195657798,277.1727326351456 C246.7011586330254,277.1180684458666 246.71377344593594,277.0343519601874 246.72868186119388,276.9208186439924 C246.74855974820446,276.78243796903416 246.7730248399098,276.60697738946004 246.80284167042564,276.3944369052701 C246.81775008568357,276.2908425325803 246.8326585009415,276.18189642108007 246.84718464914152,276.0679808378272 C246.93128340187857,275.45061953932566 246.9905347958524,275.0603248732142 247.02493883106303,274.89709683949275 C247.18319739303183,273.97315736055896 247.3089632550795,273.26902143991515 247.40300095132181,272.78507134461927 L249.90073390761205,269.8794594375543 L249.88582549235414,269.89436785281225 L247.58840047440123,271.8802452185802 L247.88465744427037,270.4650925702505 C248.0578244214971,269.7582807802014 248.19582282939743,269.1952014039211 248.29941720208714,268.77508990729376 C248.3143256173451,268.7058995698146 248.329234032603,268.64397230643556 248.34414244786092,268.5900726512723 L248.4702905769665,268.7234838544779 L250.89386372402498,266.04799671626614 L248.49246206632444,268.01934793383407 C248.51233995333502,267.94557039166017 248.5318355732877,267.87867365652846 248.5517134602983,267.8194222625546 C248.76425394448827,267.0189550433211 248.87778726068328,266.59158047259376 248.8926956759412,266.53729855037255 L249.3965236582477,264.8105982498579 C249.42634048876357,264.7165605536155 249.46838986513205,264.5854429527573 249.52267178735326,264.4176277143411 L252.87286028275082,262.4535395708732 L249.7302427997906,263.78038852882906 C249.75012068680115,263.7111981913499 249.7722921761591,263.64200785387084 249.79713953492234,263.57281751639175 C249.8269563654382,263.47916208720727 249.8563909288962,263.3828307886176 249.88582549235414,263.28382362062257 C249.8907949641068,263.27885414887 249.89308856645414,263.27159107476996 249.89308856645414,263.2612698642067 C250.036438713165,262.8465101063899 250.1698499163706,262.4608026449732 250.29332217607092,262.1052942811303 C250.35754304179738,261.9176011557035 250.41947030517647,261.73984697378205 250.4783394320924,261.57164946830795 C250.49324784735035,261.53686316603944 250.50548039320302,261.5024591308288 250.5154193367083,261.4680550956182 L250.5597623154242,261.55674105305 L255.473423077615,258.7405796375327 L250.82658472183536,260.64503411996884 C251.10793327644657,259.89923109001444 251.2986845383365,259.40992925590797 251.39730943927358,259.17751088470743 L251.63431501516888,258.62169458252714 L251.33805804529976,259.14807632124945 C251.03644933662008,259.73103358454034 250.7799481407721,260.2425069080047 250.56740765658208,260.6824962916426 C250.55249924132417,260.70696138334796 250.5402666954715,260.7341023444585 250.53032775196624,260.7639191749744 L250.2336885150392,260.8824219629221 L250.35983664414476,261.1347182211332 C250.32543260893414,261.2039085586123 250.29332217607092,261.2753924984388 250.26350534555505,261.3495523076706 C250.18437606457064,261.512780341392 250.11021625533888,261.67791971040293 250.04102591785977,261.84611721587703 C249.98674399563862,261.9550633273773 249.9347556757648,262.0685966435723 249.88544322529623,262.1874816985778 C249.75203202209065,262.4887081401996 249.62129668829033,262.7975799229793 249.4928549568374,263.11371477985904 L249.4928549568374,263.12136012101695 L249.31510077491592,262.75820641601604 L244.81619977054189,264.95203706127927 L244.97942780426334,264.4111291743569 C245.21643338015866,263.7092868560605 245.3869244879801,263.1928440608434 245.49051886066985,262.8618007887058 C245.5990827051122,262.5506354035787 245.70573521426508,262.2539961666517 245.80894731989693,261.9726476120405 L245.90527861848662,262.17257328331993 L250.7375164973457,259.8158968713932 L250.54485390016626,259.41566326177644 L245.91254169258664,261.67600837511344 C246.0314267475922,261.3495523076706 246.14457779672932,261.0483258660488 246.25352390822957,260.77194678319023 C246.29786688694549,260.6484745234899 246.34488573506664,260.52958946848435 246.39419818553517,260.41605615228934 C246.39419818553517,260.40611720878405 246.39649178788255,260.39617826527876 246.40184352669309,260.3862393217735 C246.76767310109923,259.49211667335555 246.98480078998398,258.96573493463325 247.05399112746306,258.8078586397223 L247.29864204451633,258.25204233754204 L247.0096481487472,258.78568715036437 C246.69351329186748,259.428278074687 246.44886237481427,259.93439965934084 246.2760776646454,260.3051987054996 C246.27110819289277,260.3090213760786 246.2688145905454,260.3139908478312 246.2688145905454,260.3193425866417 zM244.8234628446419,265.440192094212 L249.47030120042155,263.17984698087497 C249.46074452397417,263.19972486788555 249.45080558046888,263.21960275489613 249.4404843699057,263.2390983748488 C249.38123297593188,263.38741799331234 249.3242751843054,263.5330617423706 249.27037552914214,263.67641188908146 C249.2206808116157,263.79988414878176 249.17404423055243,263.9187692037873 249.12931898477862,264.0323025199823 L248.78069142797779,264.1806221384458 L248.95118253579926,264.51395901293085 C248.6549255659301,265.2704655205063 248.42977026882957,265.8828573472552 248.27686344567132,266.3522812943511 C248.22258152345012,266.50060091281455 248.16065426007103,266.6806486970834 248.0914639225919,266.89318918127344 L247.99513262400222,266.693263509994 L243.74126480373928,268.77585444140954 C243.74126480373928,268.76629776496213 243.74355840608666,268.7609460261516 243.7485278778393,268.7609460261516 C243.78828365186047,268.57363516778275 243.8276571588237,268.40773126465604 243.86741293284484,268.26438111794516 C243.88690855279754,268.1756951605134 243.90449283746074,268.09656587952895 243.91901898566078,268.02737554204987 C244.15143735686132,267.1676569288425 244.32919153878282,266.53768081743044 244.45266379848312,266.1374472078137 L244.7267492789943,265.2406486899905 L244.8234628446419,265.440192094212 zM255.62938803723642,261.3419069665126 C255.56516717150998,261.3965711557917 255.5009463057835,261.45582254976557 255.43672544005702,261.520043415492 C255.15002514663527,261.79680476540847 254.81630600509237,262.19206890327257 254.4363325495441,262.7058358290844 C254.04106841168,263.24445011365935 253.66797576317379,263.8300832463555 253.3170546040256,264.4627352271728 C253.22301690778323,264.62558099383637 253.13394868329357,264.7911026299052 253.05061446467232,264.9593001353793 C252.85260012868235,265.3247474427275 252.66490700325556,265.7104549041443 252.48677055427623,266.11527571845573 C252.4175802167971,266.268182541614 252.35106574872324,266.42414750123544 252.28684488299677,266.58240606320425 C252.17331156680177,266.84425899786277 252.0643654553015,267.11108140427393 251.96038881555387,267.3828732824378 C251.64960569748473,268.19786664987134 251.36749260875774,269.04764631957335 251.11596088466237,269.9322122915439 C251.02192318842003,270.2533166201763 250.93553083333563,270.57939042056125 250.8564015523512,270.9108159597568 C250.67864737042973,271.60271933454794 250.52077107551884,272.3137360622339 250.38200813350272,273.0450129439883 C250.3472218312342,273.23270606941503 250.31281779602358,273.4203991948418 250.27841376081298,273.6084745873265 C250.12015519884417,274.4980100310497 249.98941986504386,275.4146864358835 249.88582549235414,276.35812153476996 C249.82160462662767,276.91623143929763 249.76961630675385,277.4842802873306 249.7302427997906,278.0626503459267 C249.7153343845327,278.24575626665876 249.70042596927476,278.43344939208555 249.6858998210747,278.6261119892649 C249.55745808962178,280.5924937350802 249.53031712851117,282.6724087970905 249.60447693774296,284.8662394423537 C249.60944640949558,285.0493453630857 249.6167094835956,285.23436261910723 249.6266484271009,285.42205574453396 C249.6610524623115,286.23246190727275 249.70807131043267,287.05739421821164 249.76770497146438,287.89761721146624 C249.77267444321703,287.9568686054401 249.77726164791176,288.01611999941395 249.7826133867223,288.07537139338774 C249.81243021723816,288.5004523617677 249.8468342524488,288.93012053484244 249.88620775941206,289.3651404467277 C249.91067285111734,289.6464890013389 249.93819607928583,289.9305134253554 249.9676306427438,290.21721371877715 L249.9676306427438,290.2321221340351 L250.1530301658232,292.72947282326743 C250.3013497842867,294.23178236079735 250.5039513249714,295.6568739526324 250.7608347878773,297.00589439994616 C250.7956210901458,297.1890003206782 250.83002512535643,297.37172397435234 250.86442916056703,297.55482989508437 C250.9187110827882,297.84114792144817 250.97796247676206,298.1228787431173 251.0421833424885,298.3996400930338 C251.24478488317322,299.3136406284623 251.46726431086847,300.16342029816434 251.7092393585164,300.9489791021399 C251.72414777377438,301.003643291419 251.74134979137966,301.05754294658226 251.76122767839024,301.11220713586135 C252.09724042228055,302.179496761506 252.46803946843931,303.1305772015504 252.87286028275082,303.9654484559946 C252.95695903548787,304.13326369441074 253.0429691235144,304.29916759753746 253.13241961506196,304.462013364201 C253.87822264501642,305.8458201137833 254.73794125822377,306.8511824760489 255.71119318762612,307.47886498511355 C255.90920752361606,307.60730671656654 256.11142679724287,307.72084003276154 256.31899780968024,307.8198472007565 C256.2054644934852,307.75562633503 256.08466810319015,307.68146652579827 255.95622637173722,307.59736777306125 C255.89200550601075,307.557994266098 255.83007824263166,307.51594488972944 255.77120911571572,307.4716019110136 C255.05445838216136,306.9628044569545 254.39237183788606,306.22655810344736 253.78456721583197,305.26324511755035 C253.62172144916843,305.0063616546445 253.46346288719963,304.736863378828 253.31055606404135,304.45551482421683 C253.22187010660957,304.2876995858006 253.13777135387252,304.1195020803265 253.05864207288812,303.9516868419103 C252.64388231507132,303.10687664396096 252.2780527406652,302.16267701095865 251.9615356167276,301.1206170111351 C251.94700946852754,301.06136561716124 251.92980745092223,301.0044078255348 251.90992956391165,300.9501259033136 C251.60832085523197,299.92259205169006 251.35411326173136,298.80369637322946 251.14654224929404,297.5930566008739 C251.11175594702553,297.4099506801419 251.08232138356755,297.229902895873 251.05785629186224,297.0517664468937 C250.78109494194575,295.30748186171576 250.59607768592429,293.38085588992163 250.50203998968195,291.2711239973955 C250.487131574424,290.96492808402104 250.47489902857137,290.6583499035887 250.46496008506608,290.35215399021433 C250.45005166980815,289.9423637041502 250.44011272630286,289.5272216792755 250.4351432545502,289.10711018264817 C250.42023483929228,288.8303488327317 250.4080022934396,288.55396974987315 250.39806334993432,288.2768261328988 C250.39309387818167,288.21795700598284 250.3904180087764,288.1583233449511 250.3904180087764,288.0990719509773 C250.35601397356578,287.3131308799438 250.3384296889026,286.5134281948261 250.3384296889026,285.69805256033465 C250.33346021714996,285.51035943490785 250.33346021714996,285.32457764477056 250.3384296889026,285.14223625815436 C250.34339916065525,283.220197491055 250.4198525722344,281.2190294429712 250.5681721906979,279.1391143809609 C250.58308060595581,278.9460695167236 250.59760675415586,278.75608278894947 250.61251516941377,278.5683896635227 C250.6274235846717,278.34591023582743 250.64462560227702,278.1261066775374 250.6645034892876,277.9085967215948 C250.77306733372995,276.6043015200548 250.9091544063408,275.368814388936 251.07200017300437,274.20289986235423 C251.0964652647097,274.0052677934222 251.1239884928782,273.8103115938954 251.15304078927824,273.61764899671596 C251.2619869007785,272.87184596676155 251.38316555813145,272.1528016308598 251.51657676133703,271.4608982560687 C251.58576709881615,271.1099770969205 251.65457516923738,270.76670127893016 251.72414777377438,270.43068853503985 C251.99593965193816,269.1657668404631 252.30939863941262,268.004821785634 252.66528927031348,266.9474711034946 C252.71957119253466,266.77468639332574 252.77614671710325,266.6064888878517 252.83578037813493,266.44364312118813 C252.98371772954056,266.01894441986605 253.139682689162,265.6110654690914 253.30252845582555,265.2207708029799 C253.38165773680993,265.0430166210584 253.46078701779436,264.86755604148436 253.53991629877876,264.69477133131545 C254.10299567505905,263.4497275237493 254.7425284629185,262.4023157851152 255.45927919647286,261.55215384835526 C255.51317885163616,261.4753181697182 255.57051891032052,261.406510099297 255.62938803723642,261.3419069665126 zM255.31784038505148,264.18788521254584 C255.03649183044027,264.61755338562057 254.76469995227646,265.11450056088495 254.50246475056002,265.6771976701073 C254.42333546957565,265.85036464733406 254.3472643250544,266.0307946986608 254.27272224876475,266.21848782408756 C254.11981542560648,266.58393513143585 253.97149580714296,266.9746120646052 253.82814566043209,267.389371822422 C253.76889426645823,267.5571870608382 253.71193647483182,267.7303540380649 253.6576545526106,267.9077259529285 C253.5540601799209,268.2341820203714 253.45275940957856,268.57248836660904 253.35413450864147,268.9230272586994 C253.1412117573936,269.6890904427223 252.9466378249247,270.48458819020317 252.76850137594533,271.309520501142 C252.69434156671355,271.6455332450323 252.62515122923446,271.9865154606752 252.56054809645008,272.33208488101286 C252.43248863205503,272.9991408970408 252.31857304880214,273.6860748000793 252.21994814786504,274.3928865901284 C252.1901313173492,274.5905186590604 252.1629903562386,274.7881507279925 252.13852526453326,274.9857827969246 C251.95541934380122,276.32486430073305 251.81436279943773,277.728166670268 251.71612016555855,279.19568990552943 C251.70121175030062,279.38835250270887 251.68897920444795,279.5833087022356 251.67865799388477,279.7809407711677 C251.589972036453,281.30771540040297 251.5452467906792,282.89832862830684 251.5452467906792,284.55354498899504 C251.5452467906792,284.90446614814323 251.54792266008445,285.2527114378862 251.5528921318371,285.5982808582239 C251.5528921318371,285.78597398365065 251.55556800124236,285.9740493761353 251.56015520593712,286.1617425015621 C251.57506362119506,286.9522707772903 251.59991097995828,287.73056650716586 251.63431501516888,288.4962474241309 C251.63431501516888,288.5554988181047 251.63699088457417,288.61513247913643 251.6423426233847,288.67400160605234 C251.6767466585953,289.3509965655856 251.71841376790593,290.01575897926614 251.7677262183745,290.6679065800361 C251.7921913100798,290.97410249341056 251.82009680530618,291.2806806738429 251.84953136876413,291.58687658721726 C252.03225502243828,293.6025707835011 252.3017532982547,295.4951749871425 252.65726166209768,297.26392466402575 C252.69204796436617,297.4367093741946 252.72912786898206,297.61216995376867 252.76850137594533,297.79030640274806 C252.94128608611413,298.6152387136869 253.13662455269883,299.413412330573 253.35413450864147,300.1840627192907 C253.42791205081534,300.4558545974545 253.50474772945233,300.7200011344604 253.58349474337888,300.9772668644242 C253.60375489744735,301.036518258398 253.62095691505263,301.0934760500245 253.63586533031057,301.14737570518776 C253.96193913069555,302.18026129562185 254.31515389219115,303.07438394403977 254.69512734773946,303.8305081845574 C254.77960836753437,304.00329289472626 254.86829432496617,304.17149040020035 254.96194975415062,304.33433616686386 C255.0758653374035,304.54190717930123 255.19436812535116,304.73724564588593 255.31784038505148,304.91996929956 C256.07855183026385,306.0759448826365 256.87901904949734,306.65393267417477 257.719242042752,306.65393267417477 C258.8262874424179,306.65393267417477 259.82897393527816,305.74490161049886 260.7280660554487,303.9264572160892 C260.8022258646805,303.76858092117834 260.8786792762596,303.6053528874569 260.95780855724405,303.4375376490407 C261.22960043540786,302.8148246117286 261.49374697241376,302.10610148639006 261.75063043531964,301.3106037389092 C261.76553885057757,301.2662607601933 261.7804472658355,301.22191778147743 261.79535568109344,301.1771925357036 C261.8939805820305,300.86105767882395 261.9903118806202,300.5300144066863 262.08434957686256,300.1836804522328 C262.1932956883628,299.798355257874 262.2968900610525,299.4080605917625 262.39551496198965,299.0127964538984 C262.4253317925055,298.8747980459981 262.4574422253687,298.73871097338724 262.49184626057934,298.6056820372395 C262.80798111745906,297.2516921181731 263.07250992152285,295.81627931577486 263.2846681386549,294.2994436300449 C263.3144849691708,294.07696420234964 263.3439195326288,293.8548670417123 263.3733540960867,293.632387614017 C263.4180793418605,293.2619708349161 263.46012871822904,292.8888781864099 263.49950222519226,292.5134919355564 C263.50485396400285,292.4637972180299 263.5090589016397,292.41945423931406 263.51441064045025,292.3796984652929 C263.5690748297293,291.86096206772845 263.61800501313996,291.3349625960641 263.6627302589137,290.8013177832417 C263.6722869353611,290.64802869302554 263.6826081459243,290.4947396028094 263.6921648223717,290.3414505125932 C263.7762635751087,289.20994002122205 263.8332213667352,288.0440254946403 263.8622736631353,286.8437069328479 C263.8676254019458,286.67589169443175 263.8722126066406,286.5103700583629 263.8771820783932,286.34714202464147 C263.8871210218985,285.75883302254005 263.89209049365115,285.1609673439913 263.89209049365115,284.55354498899504 C263.89209049365115,284.27219643438383 263.89209049365115,283.9954350844674 263.89209049365115,283.72364320630356 C263.8871210218985,283.54053728557153 263.88444515249324,283.3604895013027 263.88444515249324,283.1823530523233 C263.87488847604584,282.70337242878 263.8618913960774,282.2316548793368 263.84736524787735,281.76720040399357 C263.83780857142995,281.44074433655067 263.8251937585194,281.12002227497624 263.81028534326146,280.8035051510386 C263.76059062573506,279.6570862444095 263.6864308165033,278.5500408447437 263.5878059155662,277.482751219099 C263.56334082386087,277.23083722794576 263.53849346509764,276.9812168391399 263.5140283733923,276.7342723197393 C263.47427259937115,276.3588860688858 263.43260549006055,275.98846928978486 263.38788024428675,275.62263971537874 C263.3534762090761,275.3607867807202 263.31868990680766,275.1016097154669 263.28428587159704,274.84472625256103 C263.0522497674544,273.15969306135696 262.75331692817997,271.5736670381479 262.38748735377385,270.0866481829338 C262.2888624528367,269.69138404506964 262.1875616824944,269.30338298130556 262.0835850427468,268.9230272586994 C262.0786155709941,268.90811884344146 262.0759397015889,268.8935926952414 262.0759397015889,268.8786842799835 C261.5078908535559,266.8629900836997 260.85803685513326,265.29913554984853 260.12675997337885,264.18750294548795 C259.35572731760334,263.03152736241145 258.55334876308035,262.4531573038153 257.71809524157834,262.4531573038153 C257.47573792687245,262.4531573038153 257.2360564815719,262.50285202134177 256.9990509056766,262.60147692227883 C256.83582287195514,262.6660800550632 256.67756430998634,262.754766012495 256.52465748682806,262.86829932869 C256.11601400193763,263.1553818891697 255.7138690570314,263.59498900574965 255.31784038505148,264.18788521254584 zM260.8026081317384,271.5992789310269 L259.90580961391515,270.25790382487105 L258.045315843137,278.5213708154015 L258.51244618788553,267.93066197640223 C258.44822532215903,267.7475560556702 258.3545698929746,267.58929749370145 258.2307153662164,267.4562685575537 C257.9837708468158,267.19441562289524 257.704715894552,267.1993850946478 257.3935505094249,267.4711769728117 L256.6527169512231,278.7954562959127 L253.68097284314226,272.5775003321819 L252.94013928494047,274.99342813808244 L255.72648386994194,280.8409673227124 L252.65840846327137,277.9579091720633 L252.3839407157023,280.1888197219424 L252.9026771132667,280.5148935223274 C253.31781913814137,280.80159381574913 253.69549899134228,281.0978507856183 254.03686347404312,281.4044289660506 C255.11867924788783,282.41705440241617 255.62059589490485,283.40521474707646 255.54146661392042,284.3689100000314 L255.59307266673636,284.80622351426405 C255.61333282080483,285.1667013498597 255.56363810327838,285.5252678501658 255.44513531533073,285.8811584810667 C255.3262502603252,286.24163631666227 255.15078968075107,286.5826185323052 254.91875357660842,286.9037228609376 C254.81515920391865,287.04210353589576 254.69895001831838,287.1808664779119 254.57050828686545,287.31924715287016 C254.07661924806428,287.82269286811874 253.40918096497842,288.26268225175664 252.56972250583956,288.63806850261017 L252.47300894019196,290.77264775389955 L255.17143210187743,288.45305124658864 L255.54911195507833,288.49013115120454 C255.7215143981893,288.62851182616276 255.59613080319951,288.9893719288163 255.17143210187743,289.5723291921072 L252.84419025340867,293.2852891254477 L253.39962428853107,295.7012169313483 L256.000951617511,290.587630497878 L256.4233567164857,290.2019230364613 C256.6408666724284,290.0883897202663 256.8212967237551,290.15261058599276 256.96464687046597,290.39496790069865 C257.0235159973819,290.4935928016357 257.0758865843136,290.6193586636834 257.1198472959716,290.77264775389955 L259.0694092912395,301.17833933687734 L259.90695641508887,299.50324508917856 L257.950131345721,290.31316275030895 C257.89087995174714,290.00199736518186 257.85915178594183,289.74970110697075 257.8538000471313,289.55703850979137 C257.8339221601207,289.16674384367985 257.9596880221684,289.2630751422696 258.2314799003322,289.84603240556044 L260.55107640764305,297.3686658378891 L261.10727497688123,295.7012169313483 L258.6018966794331,288.2680339905672 C258.4684854762275,287.8330140786819 258.3797995187957,287.41557845145985 258.3350742730219,287.0153448418431 C258.2612967308481,286.21029041791485 258.47345494798014,285.88421661752983 258.97269572559185,286.0371234406881 L261.94443983367273,288.08263446748776 L261.94443983367273,286.1334547392778 L258.97269572559185,284.9254908363275 C258.84922346589155,284.8662394423537 258.7700941849072,284.80201857662723 258.73530788263866,284.7328282391481 C258.65159139695953,284.5894780924372 258.82399384007044,284.4981162656002 259.25404428020306,284.458360491579 L262.12983935675214,284.458360491579 L262.0407711322624,283.1613283641391 L259.0690270241816,283.34634562016055 C258.93064634922337,283.30200264144463 258.79952874836516,283.190762927597 258.67643875572276,283.0130087456755 C258.42949423632217,282.6525309100799 258.3427196141798,282.14564479131025 258.41649715635367,281.49349719054027 L260.8255441552121,271.68834715551657 C260.8897650209386,271.9456128854804 260.9539858866651,272.207083553081 261.01858901944945,272.4742882265501 C261.0877793569286,272.7705451964192 261.1565874273498,273.0744475074463 261.2257777648289,273.3859951596312 C261.3148459893186,273.83057174796386 261.401238344403,274.2854695468597 261.4853370971401,274.74954175514506 C261.52968007585594,275.02133363330887 261.57402305457185,275.2980949832253 261.61913056740354,275.5794435378365 C261.79688474932505,276.7403885926656 261.93488315722533,277.9632609108738 262.03389032522034,279.24806049246115 C262.06332488867827,279.5989816516094 262.0885545144994,279.9548722825102 262.10805013445207,280.31535011810587 C262.13748469791005,280.8294993109755 262.16271432373117,281.35320518029255 262.18182767662597,281.88646772605705 C262.1871794154365,282.0791303232364 262.1944424895365,282.27217518747375 262.2043814330418,282.4648377846531 C262.21928984829975,283.11698538542316 262.2265529223997,283.7813655320458 262.2265529223997,284.458360491579 C262.2265529223997,284.7595869332008 262.22387705299445,285.0585197724752 262.21928984829975,285.35554127646014 C262.21928984829975,285.53329545838164 262.21661397889443,285.7110496403031 262.21164450714184,285.8891860892825 C262.1871794154365,287.2034202343277 262.1271634873469,288.46834192890447 262.03350805816245,289.6835689059548 C262.0189819099624,289.8418274679236 262.00636709705185,290.0023796322398 261.99642815354656,290.1656076659612 C261.9467334360201,290.72906930929946 261.8901579114516,291.28220974207443 261.8259370457251,291.82579349840205 C261.8159981022198,291.87013647711797 261.8114108975251,291.91715532523915 261.8114108975251,291.96646777570766 C261.756746708246,292.372053124135 261.7024647860248,292.77419806904123 261.6481828638036,293.174431678658 C261.6084270897825,293.41181952161116 261.5717294522245,293.64882509750646 261.53694314995596,293.8858306734018 C261.31943319401336,295.19547761375236 261.0506994523127,296.43058247781323 260.72921285662244,297.5915275326423 C260.66002251914335,297.84344152379555 260.5908321816642,298.0854165714435 260.52164184418507,298.3174526755862 C260.47232939371656,298.4657722940497 260.4253105455954,298.61179831016585 260.38096756687946,298.7551484568767 C260.0743893864472,299.6989658228211 259.75099145546744,300.48681822914403 259.4100092398245,301.1194702099614 C259.38057467636656,301.1687826604299 259.3530514481981,301.21580150855107 259.32858635649274,301.260144487267 C258.6565608687122,302.44096742910665 257.91993224814723,303.03157003355545 257.1198472959716,303.03157003355545 C256.2949149850328,303.03157003355545 255.54146661392042,302.4115328656487 254.85950218263457,301.17145852983515 C254.82509814742397,301.1167943405561 254.7952813169081,301.0625124183349 254.7708162252028,301.00823049611375 C254.34573525682282,300.20776327688026 253.9527647213061,299.1699082146935 253.59228688571045,297.8954298436694 C253.5628523222525,297.7964226756744 253.53341775879454,297.69550417239 253.50360092827867,297.5915275326423 C253.4837230412681,297.5173677234106 253.4638451542575,297.4432079141788 253.44473180136274,297.36904810494707 C252.98486453071428,295.64961087853237 252.63700150802921,293.7646520160489 252.399613665076,291.71417151749654 C252.36520962986538,291.41294507587475 252.33309919700216,291.1090427648477 252.3032823664863,290.8028468514733 C252.23906150075982,290.1602559271507 252.187073180886,289.5054324569754 252.14769967392277,288.8383764409475 C252.14273020217013,288.774155575221 252.13776073041748,288.71261057889984 252.13317352572273,288.653359184926 C252.08844827994892,287.902204416161 252.0563378470857,287.13384762979075 252.03645996007515,286.3486710928731 C252.03149048832248,286.15562622863575 252.02919688597513,285.9656395008616 252.02919688597513,285.77794637543485 C252.01925794246984,285.3429264635496 252.0142884707172,284.90331934696957 252.0142884707172,284.4587427586369 C252.0142884707172,282.92202918589635 252.05863144943308,281.4548882176928 252.14769967392277,280.0561730528526 C252.1626080891807,279.8539537792258 252.17713423738073,279.65593944323587 252.19204265263863,279.46327684605643 C252.2956370253284,278.02557044131083 252.44892611554454,276.662023845797 252.65152765622923,275.37225479245706 C252.68096221968722,275.17462272352503 252.71345491960835,274.9819601263456 252.74785895481895,274.7942670009188 C252.86177453807187,274.11230256963296 252.9925098718722,273.45250962770507 253.1408294903357,272.81527044219297 C253.21460703250955,272.4792576983027 253.29373631349395,272.14821442616505 253.3774527991731,271.8221406257801 C253.41720857319424,271.65891259205864 253.45964021662067,271.4956845583372 253.50360092827867,271.3328387916737 C253.79030122170042,270.28542705303954 254.09649713507486,269.3886285352163 254.42257093545982,268.64282550526184 C254.49634847763372,268.4750102668457 254.57089055392333,268.31636943781893 254.64505036315512,268.16843208641336 C254.8228045450766,267.79304583555984 255.01049767050336,267.46429616576955 255.20812973943544,267.18294761115834 C255.31707585093568,267.0197195774369 255.4283155647833,266.876369430726 255.54184888097834,266.7528971710257 C256.0361201868374,266.1798788512401 256.56211965850184,265.8931785578184 257.1202295630295,265.8931785578184 C258.52391419962237,265.8931785578184 259.7265263637621,267.7066534804754 260.7295951236803,271.3328387916737 C260.7532956812699,271.4215247491054 260.7781430400331,271.51021070653724 260.8026081317384,271.5992789310269 zM242.23704393091987,293.6847582009487 L242.35554671886752,293.8552493087701 L245.3792791468222,291.7650130361967 C245.39418756208013,291.9282410699181 245.40909597733804,292.05668280137104 245.42400439259598,292.1507204976134 L246.10596882388185,295.97492014480156 L245.9503861313183,295.8193374522381 L243.20073918387482,298.6947502617292 L243.14148778990102,298.4722708340339 C243.09217533943246,298.314394539123 243.0107524561007,297.95850390822216 242.89683687284776,297.40536347544713 L242.66709437105249,296.3155200933866 C242.65218595579455,296.2363908124022 242.63269033584186,296.14273538321777 242.60784297707866,296.0341715387754 C242.56311773130489,295.8166615828328 242.51151167848894,295.5372243635111 242.45226028451515,295.196624414926 L242.23704393091987,293.6847582009487 zM245.17209040144274,289.6824221047811 C245.18202934494803,289.7913682162814 245.19196828845332,289.89993206072376 245.20190723195861,290.008878172224 C245.26115862593244,290.65146909654663 245.31047107640097,291.162942420011 245.35022685042213,291.5432981426172 L245.2389871365745,291.3800701088958 L242.20760936746188,293.4771871885113 L241.95569537630865,291.67632707876487 C241.93581748929807,291.52800746030135 241.89376811292956,291.1258625153951 241.8295472472031,290.4683631758146 L241.7332159486134,289.24549085760634 C241.7332159486134,289.2256129705958 241.7332159486134,289.20382374829575 241.7332159486134,289.1789763895325 C241.71830753335547,288.84296364564227 241.70339911809754,288.5612328239731 241.6888729698975,288.3337839245252 C241.68390349814484,288.29402815050406 241.68122762873958,288.25503691059873 241.68122762873958,288.2152811365776 L241.83681032130312,288.422469881957 L245.08302217695308,285.96181683028266 L245.097930592211,288.422469881957 C245.11283900746895,288.6946440271787 245.1250715533216,288.9266801313214 245.13501049682688,289.1193427285008 C245.1499189120848,289.38616513491195 245.16215145793745,289.5742405273966 245.17209040144274,289.6824221047811 zM245.21643338015866,281.0336299198918 L245.12774742272686,282.08601113027856 C245.1078695357163,282.3727114237003 245.0879916487057,282.72860205460114 245.06849602875303,283.1533007559232 C245.06849602875303,283.2125521498971 245.06620242640565,283.2767730156235 245.06085068759512,283.34596335310266 L245.08302217695308,285.7102851061873 L244.89035957977364,285.4656341891341 L241.66631921348164,287.9113788255505 L241.60706781950782,285.51724024195 C241.60706781950782,285.487805678492 241.60706781950782,285.45798884797614 241.60706781950782,285.4285542845182 C241.60706781950782,285.37885956699176 241.60706781950782,285.3322229859285 241.60706781950782,285.2878800072126 C241.60706781950782,284.7343573073797 241.61203729126046,284.39337509173674 241.62197623476575,284.2649333602838 C241.63191517827102,283.8994860529356 241.64185412177633,283.5707363831453 241.65179306528162,283.2790666179709 L241.7852042684872,283.4644661410503 L245.21643338015866,281.0336299198918 zM245.79442117169688,276.2166827233486 C245.7844822281916,276.26599517381715 245.7772191540916,276.31530762428565 245.77224968233895,276.3650023418121 C245.6686553096492,277.00224152732414 245.57958708515952,277.60240080822035 245.5054272759278,278.16586245155855 L245.46070203015398,278.19529701501654 L245.49778193476985,278.2327591866903 C245.43356106904338,278.7067703384809 245.38157274916955,279.1513469268136 245.34219924220633,279.56648895168826 L245.24586794361662,280.73737295002263 L245.11971981451103,280.5592365010433 L241.65867387232373,283.0049811374597 C241.66364334407638,282.7626238227539 241.6709064181764,282.55046560562175 241.6808453616817,282.36774195194766 C241.68581483343434,282.1800488265209 241.69078430518698,282.0191143951468 241.69575377693963,281.8857031919412 C241.70072324869227,281.84136021322536 241.70339911809754,281.79892856979893 241.70339911809754,281.75993732989355 L241.89606171527694,279.2920212041192 C241.91097013053488,279.1043280786924 241.93046575048754,278.89140532744455 241.95531310925077,278.6543997515492 L242.08872431245635,278.8397992746286 L245.79442117169688,276.2166827233486 zM242.81503172245812,272.9479171112828 L242.9113630210478,273.14784278256224 L246.85406545618366,271.2208345437102 L246.54290007105658,272.4364437878184 C246.48364867708275,272.65892321551365 246.32042064336133,273.41963466072605 246.05398050400805,274.71934265757125 C245.9847901665289,275.10963732368276 245.92056930080247,275.48769944394155 245.86131790682862,275.8535290183477 C245.85634843507597,275.8680551665477 245.85176123038124,275.8856394512109 245.84640949157068,275.9055173382215 L245.72026136246512,275.7273808892421 L241.99239301386666,278.358525048738 C242.00233195737195,278.2644873524956 242.0145645032246,278.16586245155855 242.02947291848253,278.06226807886884 C242.093693784209,277.52365379429386 242.14300623467756,277.1211265823297 242.17779253694604,276.8543041759185 C242.1827620086987,276.81951787365006 242.23704393091987,276.4242537357859 242.3410205706675,275.6681294952683 C242.41518037989925,275.1394541541986 242.47672537622043,274.74954175514506 242.52642009374688,274.4972454969339 C242.52642009374688,274.49189375812335 242.52871369609426,274.4873065534286 242.5340654349048,274.48233708167595 C242.56349999836277,274.3145218432598 242.59331682887864,274.1539696789436 242.6227513923366,274.00029832166956 C242.69652893451047,273.58553856385277 242.7607498002369,273.2346174047045 242.81503172245812,272.9479171112828 zM247.995897158118,267.18944615114253 C247.98098874286006,267.23378912985845 247.96608032760213,267.27813210857437 247.95155417940208,267.3228573543482 C247.86248595491242,267.58929749370145 247.7661546563227,267.8909062023811 247.66256028363298,268.2269189462714 L247.36630331376384,269.23495717794225 C247.2130142235477,269.79841882128045 247.1216523967106,270.1416946392708 247.09221783325268,270.2651668989711 L246.9217267254312,270.939485989099 L246.82539542684148,270.73956031781955 L242.86778457644772,272.67421389782953 C242.90754035046888,272.4811690335922 242.93697491392683,272.3309380798392 242.9564705338795,272.2219919683389 L243.423600878628,270.0579781535916 C243.51763857487032,269.68259190273807 243.60135506054948,269.34657915884776 243.67551486978124,269.0499399219207 L243.77184616837093,269.2498655932002 L247.995897158118,267.18944615114253 zM256.61487251249144,281.5745378068142 C256.8075351096709,280.77407058758064 257.03727761146615,280.3738369779639 257.3041000178773,280.3738369779639 C257.57130469134637,280.3738369779639 257.79837132373643,280.77407058758064 257.98644671622105,281.5745378068142 C258.09004108891077,281.9992365081362 258.16649450048993,282.47401219404264 258.2161892180164,282.9977180633597 C258.2307153662164,283.1903806605391 258.24333017912693,283.38801272947114 258.2532691226323,283.59061427015587 C258.2681775378902,283.8677578871302 258.27582287904806,284.15636951584145 258.27582287904806,284.4579782245211 C258.27582287904806,285.5894887158923 258.1794915804584,286.5554775711946 257.986828983279,287.3559447904281 C257.9226081175525,287.6223849297814 257.85532911536285,287.8448643574767 257.78652104494165,288.023000806456 C257.7077740310151,288.2206328753881 257.6209994088728,288.363983022099 257.5269617126305,288.45266897953076 C257.45777137515137,288.51688984525725 257.38361156591964,288.5490002781205 257.3044822849352,288.5490002781205 C257.1615144052822,288.5490002781205 257.030396804424,288.4377605642728 256.91189401647637,288.21566340363546 C256.82817753079723,288.05740484166665 256.74904824981286,287.84754022688196 256.67488844058107,287.5856872922234 C256.6550105535705,287.51190975004954 256.6355149336178,287.43507407141254 256.6156370466072,287.3559447904281 C256.42297444942784,286.56044704294726 256.3266431508381,285.59445818764493 256.3266431508381,284.4579782245211 C256.3266431508381,283.7565181732826 256.36410532251193,283.1166031183652 256.4378828646858,282.538615326827 C256.4623479563911,282.355509406095 256.4925470539648,282.1781374912314 256.52656882211755,282.00497051400464 C256.550651646765,281.8566508955412 256.5804684772809,281.7133007488303 256.61487251249144,281.5745378068142 zM247.35827570554804,300.9034893222503 L247.20995608708452,300.7551697037868 L244.60862875810454,303.4532105984144 C244.57881192758867,303.37408131742995 244.55434683588336,303.30489097995087 244.5344689488728,303.2456395859771 C244.4109966891725,302.90427510327623 244.31466539058277,302.61298760515973 244.2454750531037,302.3710125575118 L243.25960831079078,298.9394011787824 L243.43009941861223,299.10262921250387 L246.15757487669777,296.2417425512127 L246.52072858169865,297.9466536294274 C246.69848276362012,298.63855700421857 246.79252045986243,298.9963589704089 246.80245940336775,299.02120632917206 L247.35827570554804,300.88896317405033 L247.35827570554804,300.9034893222503 zM256.8816949189026,282.7977923920803 C256.8671687707026,282.8471048425488 256.8522603554446,282.90138676477 256.83735194018675,282.96102042580173 C256.733757567497,283.3857191271238 256.6821515146811,283.90216192234084 256.6821515146811,284.50996654439496 S256.733757567497,285.6319203593187 256.83735194018675,286.0512673218302 C256.9363591081817,286.47634829021024 257.059831367882,286.6888887744002 257.2081509863455,286.6888887744002 C257.3511188659985,286.6888887744002 257.4749733927567,286.47634829021024 257.5789500325043,286.0512673218302 C257.6775749334414,285.6315380922608 257.7268873839099,285.117771166449 257.7268873839099,284.50996654439496 C257.7268873839099,284.02563418204113 257.697452820452,283.60093548071904 257.63820142647813,283.2351059063129 C257.61870580652544,283.1364810053758 257.598445652457,283.04511917853876 257.5793322995622,282.96102042580173 C257.53957652554107,282.7882357156329 257.49485127976726,282.64985504067465 257.4455388292987,282.545878400927 C257.37176128712485,282.3929715777688 257.2926320061405,282.3161358991317 257.2085332534034,282.3161358991317 C257.1737469511349,282.3161358991317 257.14163651827164,282.3283684449844 257.1118196877558,282.3532158037476 C257.0223691962082,282.4124671977214 256.946298051687,282.56040454912704 256.8816949189026,282.7977923920803 zM244.69769698259424,303.6974792484097 L244.85327967515778,303.8457988668732 L247.4400808559377,301.15540331340355 L248.07005696734976,302.91918351853417 C248.12930836132358,303.09693770045567 248.30935614559246,303.54419015819354 248.61134712133003,304.2609408917479 C248.6556901000459,304.36950473619027 248.70270894816707,304.48571392179053 248.7520213986356,304.6091861814908 L249.05592370966266,305.32020290917677 L248.8926956759412,305.1573571425132 L246.33609359273504,307.817935865467 C246.251994839998,307.6302427400403 246.12087723913976,307.33130990076586 245.94312305721832,306.9211373476438 L244.83149045285774,304.0751591016106 C244.7817957353313,303.9321912219576 244.73707048955748,303.80642535991 244.69769698259424,303.6974792484097 zM241.89644398233483,304.8240202680282 L242.22251778271982,305.5950529238038 C242.33605109891485,305.87640147841495 242.44232134100986,306.1214346625261 242.54094624194693,306.32900567496347 L243.16365927925895,307.6333008765034 C243.29707048246456,307.9100622264199 243.4083101963122,308.13483525646257 243.49699615374396,308.30761996663136 L238.89450077668022,305.60996133906167 L238.7832610628326,305.8026239362411 L238.59786153975318,305.2838875386767 C238.57339644804784,305.2196666729502 238.550842691632,305.1604152789764 238.53134707167933,305.1061333567552 C238.294341495784,304.4589552277379 238.12614399030994,303.94748190427345 238.02751908937284,303.57171338636203 L237.55312567052434,301.83736774468946 L241.4663935422022,304.22386098713207 L241.57763325604986,304.03884373111055 C241.64682359352898,304.21698018008993 241.7508002332766,304.4685119041852 241.88879864117692,304.7949679716282 C241.88879864117692,304.80414238101764 241.8910922435243,304.81408132452293 241.89644398233483,304.8240202680282 zM241.43657671168637,303.6902161743097 L237.5825602339823,301.34080283648296 L237.46367517897676,301.5262023595624 L236.9598471966703,299.6806170040421 C236.92047368970702,299.5426185961418 236.84134440872262,299.1867279652409 236.72284162077497,298.61332737839746 L236.5003621930797,297.51660318929476 C236.48545377782176,297.44741285181567 236.4632822884638,297.3315859332733 236.43346545794796,297.16835789955184 L239.8203515909035,299.15461753237764 L239.93159130475115,298.96195493519826 C239.961408135267,299.0804577231459 239.98625549403022,299.17181954998296 240.0057511139829,299.23604041570945 L240.4801445328314,300.8885809069924 L241.23626877334902,303.1267545309715 C241.29093296262812,303.2949520364456 241.35744743070194,303.48264516187237 241.43657671168637,303.6902161743097 zM236.3749785980899,275.764460793858 C236.40938263330054,275.56185925317334 236.44416893556902,275.37416612774655 236.47857297077962,275.2009991505198 L238.66475827488492,277.97281758732123 L238.83524938270637,277.83902411705776 C238.67202134898494,279.09897633988186 238.58830486330578,279.7660323559098 238.58333539155313,279.84019216514156 L238.37576437911582,282.3375428543739 C238.37576437911582,282.3474817978792 238.37576437911582,282.36009661078975 238.37576437911582,282.3746227589898 L235.90784825334143,280.344020147448 L235.76717397603582,280.5217743293695 C235.76220450428318,280.5168048576169 235.76220450428318,280.5141289882116 235.76717397603582,280.5141289882116 C235.7771129195411,280.37077884150074 235.78934546539375,280.23736763829515 235.8042538806517,280.11389537859486 C235.81419282415698,279.9854536471419 235.82413176766227,279.8692444615416 235.83407071116756,279.7656500888519 C235.85394859817814,279.5928653786831 235.87115061578345,279.4468393625669 235.88605903104138,279.32833657461924 L236.026733308347,278.120372671669 C236.03667225185225,278.05080006713195 236.0936300434787,277.65324232692046 236.19722441616844,276.92693491691875 L236.3749785980899,275.764460793858 zM237.30885702052902,271.0358172876887 C237.38798630151342,270.7147129590563 237.45947024133991,270.4257190632872 237.52369110706638,270.16845333332344 L239.27294516399692,273.78546423513217 L239.55467598566602,273.6444076907687 C239.48051617643426,274.01520673692744 239.39144795194457,274.46704639936013 239.28785357925483,275.0010734792404 C239.258036748739,275.1589497741513 239.19152228066514,275.5515380426101 239.08792790797543,276.1792205516748 L238.88800223669597,277.380303647583 C238.88303276494332,277.42464662629885 238.8780632931907,277.47128320736215 238.87309382143806,277.5209779248886 L236.70869773963284,274.7785940515451 L236.53094355771134,274.9192683288507 L236.53094355771134,274.9116229876928 C236.67926317617486,274.08669067675396 236.76565553125928,273.6145908602528 236.7901206229646,273.49608807230516 L237.23507947835515,271.33207425755785 C237.2591623030026,271.23383162367867 237.2840096617658,271.13482445568366 237.30885702052902,271.0358172876887 zM238.3608559638579,282.64947277361676 C238.34594754859995,282.98051604575437 238.32606966158937,283.50651551741885 238.30160456988403,284.2282357227258 C238.2966350981314,284.26760922968907 238.294341495784,284.3096586060576 238.294341495784,284.3540015847735 C238.28440255227872,284.517229618495 238.27713947817873,284.6900143286638 238.2717877393682,284.8727379823379 C238.26681826761555,285.01111865729615 238.26452466526817,285.43352375627086 238.26452466526817,286.13995327926204 L238.30160456988403,287.3330087669544 L235.63376277283024,285.2802346660547 L235.49308849552463,285.45798884797614 C235.51296638253518,284.5638661995582 235.53246200248788,283.8994860529356 235.55233988949846,283.4644661410503 C235.55233988949846,283.42471036702915 235.55463349184583,283.38801272947114 235.55998523065637,283.3532264272027 C235.564954702409,283.20490680873917 235.56992417416166,283.09137349254416 235.5748936459143,283.01224421155973 L235.74538475373578,280.78133366168066 L238.22094622066805,282.81958161438035 L238.3608559638579,282.64947277361676 zM235.8042538806517,292.8919363228731 C235.77978878894638,292.7241210844569 235.7450024866779,292.3265633442454 235.70065950796197,291.6988808351807 L235.6119735505302,290.59451130492016 L238.58371765861105,292.86938256645726 L238.7171288618166,292.69162838453576 L239.34710497322868,296.49327427530807 C239.36201338848662,296.6270677455716 239.40138689544986,296.8170544733457 239.46560776117633,297.0639989927463 L239.7324301675875,298.160723181849 C239.7771554133613,298.3484163072757 239.81920478972984,298.51432021040245 239.85857829669305,298.6576703571133 L236.49386365309547,296.6863191395454 L236.38262393924782,296.8789817367248 C236.3581588475425,296.7406010617666 236.33063561937402,296.5827247668557 236.30120105591607,296.4045883178763 L235.8042538806517,292.8919363228731 zM235.4777978132088,286.75502097541613 C235.4777978132088,286.2855970283203 235.48009141555616,285.9476729491405 235.48544315436672,285.7401019367032 L238.17583870783636,287.8005213787608 L238.30924991104195,287.6300302709393 L238.33906674155782,288.66788533312604 C238.3585623615105,288.9446466830425 238.38340972027373,289.3594064408593 238.41322655078957,289.9129291406922 C238.44763058600017,290.18969049060865 238.48509275767395,290.60483251548334 238.52446626463723,291.15797294825836 C238.57377871510573,291.6423053106122 238.62079756322692,292.0448325225763 238.66552280900072,292.36593685120863 L235.73047633847784,290.1128548119716 L235.58980206117224,290.2978720679931 L235.4777978132088,286.75502097541613 z\" fill=\"#1E7C84\" clip-rule=\"evenodd\" fill-rule=\"evenodd\"/>\n     <path id=\"xe_uw5e\" pointer-events=\"bounding-box\" d=\"M310.5061178005059,285.6399479675345 L266.9016790404637,290.990922243958 C266.9605481673796,290.2332689352088 267.00756701550074,289.4633830806069 267.04273558482714,288.6820292142682 C267.0480873236377,288.54403080636786 267.0545858636219,288.40794373375695 267.065289341243,288.27453253055137 C267.0821090917904,287.7825548270397 267.09587070587463,287.2871367200069 267.1054273823221,286.788660476511 L310.472478299411,284.4690639692001 L310.5061178005059,285.6399479675345 zM310.4399855994899,283.20911174637604 L267.09128350117993,282.560786816185 C267.0759928188641,281.9655970070414 267.0549681306798,281.3776702719979 267.02820943662715,280.79700661105437 C267.01865276017975,280.57949665511177 267.00833154961657,280.3646625685744 266.9983926061113,280.15173981732653 C266.9788969861586,279.86045231921 266.959019099148,279.571076156383 266.9395234791954,279.28475813001916 C266.9253795980532,279.0878905952029 266.9104711827953,278.89140532744455 266.89479823342157,278.69530232674407 L310.41437370661095,282.26032490867897 L310.4399855994899,283.20911174637604 zM186.23377314803193,272.0843758274965 L231.70596875295232,275.81224417609496 C231.60657931789945,276.59665617889686 231.52477416750978,277.3959765969567 231.46131783589908,278.2098231632166 C231.4517611594517,278.2839829724483 231.4441158182938,278.36081865108537 231.43914634654115,278.43956566501186 C231.43914634654115,278.4449174038224 231.43914634654115,278.44950460851715 231.43914634654115,278.4544740802698 C231.34052144560405,279.7985250558309 231.30076567158292,280.9025123190336 231.3206435585935,281.76758267105146 C231.3206435585935,281.8512991567306 231.3206435585935,281.93769151181505 231.3206435585935,282.0267597363047 L186.1041846154053,281.34900024265573 L186.23377314803193,272.0843758274965 zM185.97039114514183,291.12433344716356 L232.04656870153735,288.6602399919681 C232.17157002946925,291.0058306592159 232.46171072641204,293.1725203433685 232.91737305942365,295.159926777368 L185.83315727135727,300.94018695980833 L185.97039114514183,291.12433344716356 z\" fill=\"#C82F4B\" clip-rule=\"evenodd\" fill-rule=\"evenodd\"/>\n     <path id=\"xe_1fz7\" pointer-events=\"bounding-box\" d=\"M310.47286056646897,284.4690639692001 L267.1058096493799,286.788660476511 C267.1103968540747,286.5654165146999 267.1138372575958,286.34179028583094 267.11689539405893,286.1177817899041 C267.11689539405893,285.96946217144057 267.1195712634642,285.8238184223823 267.12454073521684,285.68046827567144 C267.12454073521684,285.4136458692603 267.12454073521684,285.1491170651965 267.12454073521684,284.88764639759586 C267.12454073521684,284.75882239908503 267.12454073521684,284.63038066763204 267.12454073521684,284.50193893617916 C267.12454073521684,284.25002494502587 267.12224713286946,283.99811095387264 267.11689539405893,283.7458146956615 C267.1107791211326,283.34787468839215 267.10275151291677,282.952610550528 267.09128350117993,282.56002228206916 L310.4399855994899,283.2083472122602 L310.47286056646897,284.4690639692001 zM310.4136091724951,282.26032490867897 L266.89403369930574,278.69530232674407 C266.89479823342157,278.6888037867598 266.89479823342157,278.68268751383346 266.89403369930574,278.67695350796504 C266.8022896054108,277.50339364022534 266.6856981527526,276.36041513711734 266.5461706766207,275.24916479981465 L310.3727065973003,280.80771008867544 L310.4136091724951,282.26032490867897 zM186.10380234834741,281.3486179755978 L231.3202612915356,282.0263774692468 C231.3202612915356,282.0462553562574 231.3202612915356,282.06842684561536 231.3202612915356,282.0932742043786 C231.31529181978294,283.51645446092414 231.3374633091409,284.89452720463794 231.38677575960946,286.2286392366938 C231.3917452313621,286.3918672704153 231.39939057252,286.55700663942616 231.4089472489674,286.72520414490026 C231.43799954536746,287.39034882563874 231.47393264880967,288.045172295814 231.51636429223606,288.68929228836816 L185.97039114514183,291.1239511801057 L186.10380234834741,281.3486179755978 zM231.70558648589443,275.81224417609496 L186.23339088097404,272.0843758274965 L186.32972217956376,265.07359798569007 L232.5985623331387,270.94292639262005 C232.2182066105325,272.4983710511975 231.9200383053739,274.1210947119646 231.70558648589443,275.81224417609496 z\" fill=\"#D3EDF0\" clip-rule=\"evenodd\" fill-rule=\"evenodd\"/>\n    </g>\n   </g>\n  </g>\n </g>\n</svg>","printColors":["#EFCB58","#1E7C84","#C82F4B","#D3EDF0"],"printColorNames":["No Name","No Name","No Name","No Name"],"printColorCategories":["No Category","No Category","No Category","No Category"],"cmykValue":["","","",""],"printUnit":"inch","PrintDimension":{"boundheight":"8.27","boundwidth":"11.69"},"printSize":"A4","designPrice":0,"webFontPrice":0,"isTransit":0,"noOfLines":[],"scalingPrice":0,"isWhiteBase":false,"customizeImage":"https://www.screenshotsinc.com//designer-tool/designer-assets/screenshotsinc_com/images/capturedImage/cart/ci_58b5c692f2c571.20261992.png","totalBackgroundPrice":0,"imagePresent":0}],"simpleData":{"_R!@#&":["PC"],"isObject":[1]},"nameNumberData":{},"envInfo":{"browserIp":"99.195.212.104","browserHeight":1024,"browserWidth":1280,"browserLang":"en-US","userAgent":"Mozilla/5.0 (Windows NT 10.0; Win64; x64) AppleWebKit/537.36 (KHTML, like Gecko) Chrome/56.0.2924.87 Safari/537.36","browserName":"Chrome"},"notes":"","unitPrice":"0.43"}