{"version":1.2,"sizeData":[{"is_predeco_product_template":false,"qty":12,"id":439,"refid":0,"addedprice":"0.00","simple_product":{"xe_color":"Tennessee Orange","xe_size":"L","simpleProductId":"1561"}},{"is_predeco_product_template":false,"qty":0,"id":439,"refid":0,"addedprice":"0.00","simple_product":{"xe_color":"Tennessee Orange","xe_size":"M","simpleProductId":"1562"}},{"is_predeco_product_template":false,"qty":0,"id":439,"refid":0,"addedprice":"0.00","simple_product":{"xe_color":"Tennessee Orange","xe_size":"S","simpleProductId":"1563"}},{"is_predeco_product_template":false,"qty":0,"id":439,"refid":0,"addedprice":"0.00","simple_product":{"xe_color":"Tennessee Orange","xe_size":"XL","simpleProductId":"1568"}},{"is_predeco_product_template":false,"qty":0,"id":439,"refid":0,"addedprice":"0.00","simple_product":{"xe_color":"Tennessee Orange","xe_size":"2XL","simpleProductId":"1566"}},{"is_predeco_product_template":false,"qty":0,"id":439,"refid":0,"addedprice":"0.00","simple_product":{"xe_color":"Tennessee Orange","xe_size":"3XL","simpleProductId":"1564"}},{"is_predeco_product_template":false,"qty":0,"id":439,"refid":0,"addedprice":"0.00","simple_product":{"xe_color":"Tennessee Orange","xe_size":"4XL","simpleProductId":"1567"}},{"is_predeco_product_template":false,"qty":0,"id":439,"refid":0,"addedprice":"0.00","simple_product":{"xe_color":"Tennessee Orange","xe_size":"5XL","simpleProductId":"1565"}}],"printType":"Schedule A","multipleBoundary":"false","printTypeId":"1","productInfo":{"productId":439,"variantId":"1561"},"sides":[{"url":"https://www.screenshotsinc.com//designer-tool/designer-assets/screenshotsinc_com/images/productTemplate/16/50.png","svg":"<svg width=\"500\" height=\"500\" xmlns=\"http://www.w3.org/2000/svg\" xmlns:xhtml=\"http://www.w3.org/1999/xhtml\" xmlns:xlink=\"http://www.w3.org/1999/xlink\" class=\"mainContent\">\n <!-- Created with Product Designer Tool by Riaxe-->\n <defs>\n  <mask patternUnits=\"userSpaceOnUse\" x=\"0\" y=\"0\" width=\"500\" height=\"500\">\n   <image id=\"xe_quds\" xlink:href=\"#\" x=\"0\" y=\"0\" width=\"500\" height=\"500\" xmlns:xlink=\"http://www.w3.org/1999/xlink\"/>\n  </mask>\n  <image id=\"xe_0l5j\" xlink:href=\"#\" width=\"500\" height=\"500\" preserveAspectRatio=\"none\" xmlns:xlink=\"http://www.w3.org/1999/xlink\"/>\n  <clipPath id=\"boundryClipPath0\" class=\"boundryClipPath\">\n   <rect aHeight=\"13\" aWidth=\"12\" height=\"200\" width=\"184\" y=\"151.27991\" x=\"156.72622\" id=\"boundRectangle\"/>\n  </clipPath>\n  <filter id=\"filter8483\" style=\"color-interpolation-filters:sRGB;\">\n   <feColorMatrix values=\"0\" result=\"colormatrix\" id=\"feColorMatrix8485\" type=\"matrix\"/>\n  </filter>\n  <g id=\"xe_zgwz\" type=\"patternG\" xmlns:xlink=\"http://www.w3.org/1999/xlink\"/>\n </defs>\n <g id=\"layer_background\">\n  <title>background</title>\n  <rect id=\"canvas_background\" x=\"-1\" y=\"-1\" width=\"502\" height=\"502\" fill-opacity=\"0\" stroke=\"#000000\" stroke-width=\"0\" fill=\"#fff\" opacity=\"0\"/>\n  <g id=\"bleedM\">\n   <rect isBleed=\"false\" id=\"cropM\" isbleed=\"false\" class=\"bleedRect\" width=\"0\" height=\"0\" x=\"0\" y=\"0\" fill=\"none\" stroke=\"#ff0000\" stroke-width=\"0.5\" display=\"none\"/>\n   <rect id=\"safeM\" class=\"bleedRect\" width=\"0\" height=\"0\" x=\"0\" y=\"0\" fill=\"none\" stroke=\"#2B8F49\" stroke-width=\"0.5\" stroke-dasharray=\"3,3\" display=\"none\"/>\n   <path isBleed=\"false\" pointer-events=\"bounding-box\" id=\"cropMMask\" isbleed=\"false\" class=\"bleedPath\" width=\"0\" height=\"0\" awidth=\"0\" aheight=\"0\" x=\"0\" y=\"0\" ax=\"0\" ay=\"0\" fill=\"none\" stroke=\"#ff0000\" display=\"none\"/>\n   <path pointer-events=\"bounding-box\" id=\"safeMMask\" class=\"bleedPath\" width=\"0\" height=\"0\" awidth=\"0\" aheight=\"0\" x=\"0\" y=\"0\" ax=\"0\" ay=\"0\" fill=\"none\" stroke=\"#2B8F49\" stroke-width=\"2\" stroke-dasharray=\"5,5\" display=\"none\"/>\n   <rect id=\"hAlignTleft\" class=\"bleedRect\" width=\"0\" height=\"0.5\" x=\"0\" y=\"0\" fill=\"#ff0000\" display=\"none\"/>\n   <rect id=\"hAlignBleft\" class=\"bleedRect\" width=\"0\" height=\"0.5\" x=\"0\" y=\"0\" fill=\"#ff0000\" display=\"none\"/>\n   <rect id=\"vAlignBleft\" class=\"bleedRect\" width=\"0.5\" height=\"0\" x=\"0\" y=\"0\" fill=\"#ff0000\" display=\"none\"/>\n   <rect id=\"vAlignTleft\" class=\"bleedRect\" width=\"0.5\" height=\"0\" x=\"0\" y=\"0\" fill=\"#ff0000\" display=\"none\"/>\n   <rect id=\"hAlignTright\" class=\"bleedRect\" width=\"0\" height=\"0.5\" x=\"0\" y=\"0\" fill=\"#ff0000\" display=\"none\"/>\n   <rect id=\"hAlignBright\" class=\"bleedRect\" width=\"0\" height=\"0.5\" x=\"0\" y=\"0\" fill=\"#ff0000\" display=\"none\"/>\n   <rect id=\"vAlignTright\" class=\"bleedRect\" width=\"0.5\" height=\"0\" x=\"0\" y=\"0\" fill=\"#ff0000\" display=\"none\"/>\n   <rect id=\"vAlignBright\" class=\"bleedRect\" width=\"0.5\" height=\"0\" x=\"0\" y=\"0\" fill=\"#ff0000\" display=\"none\"/>\n  </g>\n </g>\n <g clip-path=\"url(#boundryClipPath0)\" id=\"layer_area_0\">\n  <title>area_0</title>\n  <g type=\"bg_area_0\" id=\"background\"/>\n  <g type=\"bgptrn_area_0\" id=\"pbgpattern\"/>\n  <g type=\"bgBrdr_area_0\" id=\"backgroundBorder\"/>\n  <g xe_p=\"&amp;#35;&amp;#103;&amp;#81;&amp;#84;&amp;#19;&amp;#58;&amp;#122;&amp;#61;&amp;#93;&amp;#111;&amp;#0;&amp;#122;&amp;#106;&amp;#43;&amp;#26;&amp;#28;&amp;#19;&amp;#116;&amp;#33;&amp;#53;&amp;#93;&amp;#18;&amp;#11;&amp;#34;&amp;#60;&amp;#32;&amp;#75;&amp;#89;&amp;#86;&amp;#110;&amp;#122;&amp;#105;&amp;#26;&amp;#83;&amp;#94;&amp;#108;&amp;#55;&amp;#55;&amp;#75;&amp;#18;&amp;#11;&amp;#91;&amp;#122;&amp;#102;&amp;#10;&amp;#5;&amp;#7;&amp;#51;&amp;#111;&amp;#7;&amp;#26;&amp;#109;&amp;#29;&amp;#34;&amp;#40;&amp;#55;&amp;#81;&amp;#83;&amp;#84;&amp;#34;&amp;#98;&amp;#103;&amp;#8;&amp;#30;&amp;#1;&amp;#48;&amp;#122;&amp;#105;&amp;#26;&amp;#89;&amp;#66;&amp;#83;&amp;#59;&amp;#36;&amp;#84;&amp;#81;&amp;#83;&amp;#108;&amp;#61;&amp;#103;&amp;#2;&amp;#18;&amp;#0;&amp;#34;&amp;#116;&amp;#103;&amp;#91;&amp;#95;&amp;#93;&amp;#111;&amp;#42;&amp;#0;&amp;#92;&amp;#89;&amp;#69;&amp;#34;&amp;#98;&amp;#35;&amp;#89;&amp;#92;&amp;#66;&amp;#101;&amp;#116;&amp;#103;&amp;#74;&amp;#85;&amp;#66;&amp;#105;&amp;#34;&amp;#32;&amp;#26;&amp;#10;&amp;#87;&amp;#97;&amp;#52;&amp;#54;&amp;#93;&amp;#28;&amp;#19;&amp;#112;&amp;#55;&amp;#54;&amp;#81;&amp;#68;&amp;#88;&amp;#111;&amp;#54;&amp;#103;&amp;#2;&amp;#86;&amp;#80;&amp;#108;&amp;#43;&amp;#32;&amp;#20;&amp;#18;&amp;#93;&amp;#111;&amp;#59;&amp;#46;&amp;#104;&amp;#66;&amp;#94;&amp;#112;&amp;#61;&amp;#55;&amp;#76;&amp;#89;&amp;#84;&amp;#115;&amp;#122;&amp;#127;&amp;#67;&amp;#18;&amp;#82;&amp;#111;&amp;#52;&amp;#42;&amp;#74;&amp;#117;&amp;#85;&amp;#105;&amp;#44;&amp;#103;&amp;#2;&amp;#86;&amp;#80;&amp;#108;&amp;#43;&amp;#32;&amp;#20;&amp;#18;&amp;#67;&amp;#101;&amp;#43;&amp;#44;&amp;#66;&amp;#85;&amp;#19;&amp;#58;&amp;#62;&amp;#36;&amp;#84;&amp;#67;&amp;#84;&amp;#44;&amp;#122;&amp;#40;&amp;#87;&amp;#70;&amp;#84;&amp;#34;&amp;#98;&amp;#35;&amp;#89;&amp;#92;&amp;#66;&amp;#101;&amp;#116;&amp;#103;&amp;#74;&amp;#95;&amp;#69;&amp;#97;&amp;#44;&amp;#32;&amp;#26;&amp;#10;&amp;#87;&amp;#97;&amp;#52;&amp;#54;&amp;#93;&amp;#28;&amp;#19;&amp;#100;&amp;#61;&amp;#41;&amp;#93;&amp;#68;&amp;#84;&amp;#34;&amp;#98;&amp;#35;&amp;#89;&amp;#92;&amp;#66;&amp;#101;&amp;#37;&amp;#56;\" id=\"xe_1z2n\" scaled=\"true\">\n   <g id=\"xe_k9f2\">\n    <g id=\"xe_30pi\">\n     <path fill-rule=\"evenodd\" clip-rule=\"evenodd\" fill=\"#25637B\" d=\"M243.44109,171.15192C244.75425,169.37075 246.52882,168.47992 248.76531,168.47992C251.00179,168.47992 252.77636,169.33776 254.08953,171.05446C255.58492,172.88792 256.13059,175.23455 255.72806,178.09488C255.66309,178.38116 254.74636,181.33235 252.97788,186.94946C251.83375,190.44682 251.717,193.13812 252.62713,195.02334L253.66111,196.56391L254.26566,196.56391L256.05901,197.09029L256.23515,198.5532C265.45368,199.86687 273.75548,203.27286 281.14055,208.77322L282.09637,207.91487L283.89073,209.02651L286.03585,208.50013C287.53124,208.21435 289.19515,206.3875 291.02911,203.01957C293.03109,199.0674 294.48739,196.37559 295.39701,194.94517C297.06143,192.54067 299.0959,191.16203 301.50141,190.81026C303.7379,190.47271 305.65612,191.10315 307.25506,192.7026C308.80223,194.30154 309.46515,196.16088 309.24435,198.28061C308.94537,200.58157 307.62561,202.61654 305.28507,204.38451C304.83026,204.73577 302.11256,206.19816 297.1325,208.77322C293.80366,210.48941 291.82757,212.34875 291.20373,214.35073C291.0215,214.68879 290.87785,215.17659 290.7743,215.81363L291.53468,216.57402L292.4905,218.31001L291.53468,219.3242C297.20356,226.77475 300.66844,235.10904 301.92983,244.32706L303.2171,244.32706L303.89982,246.55085L305.28456,247.4285C306.59772,248.28634 309.0875,248.19548 312.7544,247.1549C314.75638,246.58283 317.70807,245.6991 321.60898,244.50269C324.46931,243.9824 326.87432,244.4702 328.82452,245.96508C330.593,247.27875 331.47774,249.05332 331.47774,251.2893C331.47774,253.51259 330.61939,255.28767 328.90319,256.61403C327.07025,258.04394 324.72361,258.53174 321.86227,258.07642C321.29021,258.01145 318.31313,257.14701 312.93003,255.48259C309.38038,254.33846 306.65711,254.22831 304.75818,255.15163L303.90033,255.75568L303.90033,257.29675L303.39324,259.09061L301.93034,259.26624C300.61717,268.54974 297.1523,276.88453 291.53519,284.26961L292.491,285.12745L291.20424,287.35074L291.45753,288.63802C291.79508,290.1329 293.59656,291.79783 296.85992,293.63077C298.69337,294.65765 301.41715,296.11446 305.03177,297.99918C307.43729,299.6636 308.80883,301.67217 309.14689,304.02541C309.43317,306.2619 308.80223,308.18012 307.25506,309.77906C305.65612,311.37851 303.79678,312.06783 301.67755,311.84651C299.38827,311.56073 297.35381,310.24097 295.57264,307.88723C295.11783,307.31517 293.66102,304.59798 291.20474,299.73466C289.48804,296.35405 287.65459,294.31959 285.70439,293.63026L284.92421,293.53331L283.98819,294.41095L282.09637,295.60077L281.14055,294.66425C273.87274,300.26815 265.57043,303.73303 256.23515,305.05939L256.05901,306.50301L254.26566,307.02939L252.88042,307.02939C252.77636,307.08116 252.69159,307.19842 252.62662,307.38014C251.71649,309.26537 251.83324,311.98255 252.97737,315.53271C254.74585,321.25387 255.66258,324.23094 255.72755,324.46545C256.13059,327.32578 255.58492,329.67242 254.08902,331.50587C252.77586,333.22257 251.00129,334.07991 248.7648,334.07991C246.52831,334.07991 244.75374,333.19618 243.44058,331.42719C241.95839,329.47699 241.47059,327.07147 241.97819,324.21115C243.18729,320.31024 244.07762,317.33316 244.64969,315.27891C245.72884,311.612 245.81361,309.14811 244.90349,307.88672L244.3766,307.02888L243.61621,307.02888L241.29546,306.34616L241.29546,305.05888C232.07643,303.798 223.74265,300.33211 216.2926,294.66374L215.27842,295.60026L213.63988,294.66374L212.43078,293.53281L211.82623,293.62976C209.82374,294.31908 207.9644,296.35354 206.24821,299.73416C203.72594,304.71422 202.29553,307.43141 201.95746,307.88672C200.12401,310.24047 198.06315,311.55972 195.77489,311.846C193.65566,312.06732 191.82221,311.378 190.27505,309.77855C188.6761,308.17961 188.04516,306.26139 188.38322,304.0249C188.669,301.67167 190.01515,299.66309 192.42016,297.99867C196.02209,296.11344 198.73928,294.65714 200.57273,293.63026C203.90157,291.79732 205.70863,290.13239 205.99492,288.63751L206.24872,287.35024L206.17055,287.09694L204.88327,285.12695L205.74112,284.2691C200.17629,276.76728 196.76979,268.43248 195.5216,259.26573L194.0587,259.0901L193.53232,257.29624L193.53232,255.75517C193.36328,255.46939 193.05111,255.26787 192.5963,255.15112C190.71107,254.22831 187.98678,254.33795 184.42445,255.48208C179.10683,257.1465 176.16173,258.01094 175.58966,258.07592C172.72934,258.53123 170.38219,258.04394 168.54925,256.61352C166.83305,255.28716 165.9747,253.51208 165.9747,251.28879C165.9747,249.05282 166.85894,247.27825 168.62691,245.96458C170.57711,244.46969 172.98263,243.98189 175.84296,244.50218C177.55915,244.83973 180.53674,245.72397 184.7752,247.15439C188.4421,248.19497 190.90599,248.28583 192.16687,247.42799L193.53232,246.55035L194.23433,244.32655L195.5216,244.32655C196.76928,235.22528 200.17629,226.89099 205.74112,219.32369L204.88327,218.38767L206.17055,216.32022L206.67815,215.81313C206.56089,215.17609 206.41775,214.68828 206.24872,214.35022C205.62437,212.34825 203.62239,210.48891 200.24177,208.77271C195.43074,206.30222 192.73944,204.83982 192.16738,204.384C189.81414,202.61603 188.52687,200.58106 188.30606,198.28011C188.02029,196.16037 188.67661,194.30103 190.27555,192.70209C191.82272,191.10315 193.68206,190.4722 195.85357,190.80976C198.20681,191.16101 200.24177,192.53966 201.95797,194.94467C202.93307,196.37508 204.42186,199.06689 206.42384,203.01906C208.25729,206.38699 209.9146,208.21334 211.3968,208.49962L213.46425,209.026L213.63988,208.77271L215.27842,207.91436L216.2926,208.77271C223.8594,203.22058 232.19419,199.81408 241.29546,198.55269L241.29546,197.26592L243.61621,196.5634L243.79184,196.5634C244.3634,195.65328 244.73445,194.97055 244.90349,194.51574C245.81361,193.30664 245.72884,190.86864 244.64969,187.20224C243.21978,182.96378 242.32894,180.01868 241.97819,178.36746C241.47109,175.49495 241.9589,173.08943 243.44109,171.15192zM248.16076,169.86516C245.06642,170.15094 243.46698,172.03616 243.36292,175.52135C243.24617,177.35429 243.58372,179.70093 244.3771,182.56176C244.78014,184.05664 245.35931,186.03324 246.1131,188.49104C246.3339,189.53111 246.56181,189.87577 246.79531,189.52451C247.08109,189.23873 247.04911,188.29561 246.69785,186.69667C245.8395,182.91302 245.64458,179.75981 246.1131,177.23754C246.39888,175.46906 247.05571,173.61023 248.08309,171.65952C248.65465,170.4626 248.68105,169.86516 248.16076,169.86516zM305.9683,193.13253C305.16273,192.39144 304.16124,191.995 302.96483,191.94272C301.36588,191.87724 299.81821,192.53407 298.32282,193.91272C297.00915,195.05685 295.63812,196.91619 294.20771,199.49023C293.46712,200.86836 292.46562,202.67542 291.20474,204.91241C290.5672,205.87431 290.28193,206.44587 290.34639,206.62861C290.45045,206.84992 291.10728,206.10223 292.31639,204.38552C294.83865,200.26381 297.06854,197.48825 299.00605,196.05783C300.6187,194.96599 302.36738,194.1919 304.25261,193.73709C305.51349,193.4508 306.08504,193.24928 305.9683,193.13253zM309.67378,249.22337C309.6088,249.3924 310.57731,249.30814 312.57979,248.97008C317.27357,247.82544 320.82271,247.4554 323.22873,247.85843C325.12614,248.19649 326.93371,248.87922 328.6499,249.90609C329.79505,250.64719 330.3661,250.93347 330.3661,250.76394C330.3661,249.68478 329.93768,248.6579 329.07933,247.6823C327.98698,246.53867 326.44032,245.90773 324.43733,245.79098C322.60438,245.7255 320.28313,246.09655 317.47458,246.90161C314.56247,247.82493 312.55999,248.3975 311.46764,248.61882C310.32401,248.85231 309.72606,249.05434 309.67378,249.22337zM250.83226,221.99671L250.4815,222.42614C251.91192,224.25908 252.62713,227.11992 252.62713,231.00712C252.62713,232.61977 252.54287,233.76999 252.37384,234.45982L252.97788,234.45982L254.44129,234.96691L254.51896,236.50748L255.47426,236.9364L256.48844,235.90293L258.04881,236.68311C259.47872,235.08366 260.21981,234.2517 260.2726,234.18673C263.13293,231.32589 265.6552,229.83761 267.8394,229.72036L267.8394,228.95946L267.58611,228.68637L267.05922,227.24327L267.58611,226.81384C263.4512,223.55048 258.66656,221.51551 253.23168,220.70994L253.23168,221.47033L252.12054,221.99671L250.83226,221.99671zM245.68417,221.99671L244.3771,221.47033L244.3771,220.70994C239.17623,221.39876 234.39768,223.37535 230.04247,226.63871L230.54957,227.24327L230.12064,228.25694L229.2628,229.21326L229.2628,229.29093C231.56426,229.45996 234.1449,230.98123 237.00573,233.85476C237.62957,234.4786 238.40316,235.42121 239.32648,236.6826L239.48232,236.50697L240.94522,235.90242L242.07666,236.93589L243.01267,236.50697L243.01267,234.9664L244.80704,234.45931L245.08013,234.45931C244.89841,233.41873 244.80704,232.26851 244.80704,231.00661C244.80704,226.95038 245.58062,224.08955 247.12779,222.42563C246.84201,222.2566 246.69887,222.11346 246.69887,221.9962L245.68417,221.9962L245.68417,221.99671zM246.62019,232.56748L248.68764,232.56748C247.93335,230.16248 247.61509,227.29504 247.73183,223.96671C247.04251,224.99358 246.5877,226.39811 246.3669,228.17928C246.13239,229.96045 246.21715,231.42335 246.62019,232.56748zM225.65427,232.89895L224.28883,233.42533L223.76194,232.89895C220.49858,237.02015 218.47021,241.86367 217.67683,247.429L218.43772,247.429L218.96461,248.71577L218.96461,249.1452L219.4717,249.47666C221.1879,248.04624 224.08071,247.33104 228.15065,247.33104L231.40741,247.58433L231.9343,246.04376L233.47487,246.04376L233.9043,245.01029L232.87032,243.97631L233.6505,242.26011L234.25505,241.75302C233.9043,241.51901 232.95458,240.71954 231.40741,239.3541C228.61206,236.54555 227.12377,234.02328 226.94104,231.7868L226.68774,231.7868L225.65427,232.89895zM230.7252,236.25368C231.75207,237.63181 232.81194,238.66579 233.9043,239.35461L235.44486,237.79424C233.39061,236.65011 231.18661,234.81717 228.83337,232.2944C229.06737,233.43853 229.69781,234.75829 230.7252,236.25368zM222.04625,249.90558C225.66087,249.90558 228.49531,250.30862 230.54957,251.1152L230.64703,248.96957C229.5034,248.56603 228.07299,248.48177 226.35628,248.71577C224.57511,248.88531 223.1381,249.28174 222.04625,249.90558zM231.40741,254.89834L228.15065,255.15214C224.14568,255.15214 221.25287,254.40394 219.4717,252.90905L218.96461,253.33848L218.96461,255.15214L218.43772,256.26328L217.67683,256.26328C218.47021,261.76363 220.49858,266.57416 223.76194,270.69587L224.28883,270.18878L225.82939,270.77354L226.86337,270.69587C226.98012,268.45989 228.46891,265.91073 231.32924,263.0504C231.84953,262.53062 232.62311,261.87378 233.6505,261.08091L232.87032,259.52055L233.9043,258.50585L233.47487,257.55055L231.9343,257.47289L231.40741,256.00998L231.40741,254.89834zM251.94491,254.97702C252.80225,254.06689 253.23168,253.00702 253.23168,251.79792C253.23168,250.6015 252.80225,249.57412 251.94491,248.71628C251.03428,247.79346 249.97492,247.33154 248.76531,247.33154C247.56889,247.33154 246.54202,247.79295 245.68417,248.71628C244.76085,249.57412 244.29893,250.6015 244.29893,251.79792C244.29893,253.00702 244.76085,254.06689 245.68417,254.97702C246.54202,255.83486 247.56889,256.26378 248.76531,256.26378C249.97492,256.26378 251.03428,255.83486 251.94491,254.97702zM240.0087,251.79792C240.0087,254.15115 240.86705,256.21201 242.58324,257.97998C244.36441,259.69668 246.42527,260.55453 248.76581,260.55453C251.11956,260.55453 253.15402,259.69668 254.87021,257.97998C256.58641,256.21252 257.44426,254.15115 257.44426,251.79792C257.44426,249.45788 256.58641,247.39601 254.87021,245.61484C253.15351,243.89864 251.11905,243.0408 248.76581,243.0408C246.42527,243.0408 244.36441,243.89864 242.58324,245.61484C240.86705,247.39601 240.0087,249.45737 240.0087,251.79792zM238.72142,241.75353C241.52997,238.94548 244.8776,237.54095 248.76531,237.54095C252.66672,237.54095 256.01384,238.94548 258.80919,241.75353C261.56597,244.56208 262.9441,247.91021 262.9441,251.79792C262.9441,255.69883 261.56546,259.04594 258.80919,261.8418C256.01384,264.64985 252.66621,266.05488 248.76531,266.05488C244.8776,266.05488 241.52997,264.64985 238.72142,261.8418C235.91287,259.04594 234.50885,255.69832 234.50885,251.79792C234.50885,247.91021 235.91287,244.56208 238.72142,241.75353zM241.2178,251.79792C241.2178,249.67818 241.95839,247.90361 243.44109,246.47319C244.87151,244.991 246.64608,244.2499 248.76531,244.2499C250.83226,244.2499 252.60733,244.991 254.08953,246.47319C255.58492,247.90361 256.33261,249.67818 256.33261,251.79792C256.33261,253.86487 255.58492,255.63944 254.08953,257.12163C252.60733,258.61702 250.83226,259.36471 248.76531,259.36471C246.64608,259.36471 244.87151,258.61702 243.44109,257.12163C241.9589,255.63944 241.2178,253.86487 241.2178,251.79792zM238.29199,241.3241C235.43167,244.18493 234.00125,247.6757 234.00125,251.79792C234.00125,255.86735 235.43116,259.33223 238.29199,262.19306C241.15283,265.11836 244.64359,266.58177 248.76531,266.58177C252.76977,266.58177 256.20876,265.11836 259.08228,262.19306C261.99438,259.26725 263.45069,255.80288 263.45069,251.79792C263.45069,247.6757 261.99438,244.18493 259.08228,241.3241C256.20876,238.46377 252.76926,237.03386 248.76531,237.03386C244.6441,237.03386 241.15283,238.46377 238.29199,241.3241zM272.05197,233.15224L271.0185,232.0411L270.23832,232.13856C270.12157,234.30957 268.63278,236.82524 265.77194,239.68607L263.27557,241.92865L263.97758,242.5134L264.56284,243.97631L263.4512,245.01029L263.97758,246.04376L265.34302,246.04376L265.85011,247.58433L268.95104,247.33104C272.90373,247.33104 275.73766,248.04574 277.45436,249.47666L278.31221,248.87211L278.31221,248.71577L278.99493,247.429L279.77511,247.429C279.03401,242.09768 277.05742,237.31304 273.84533,233.07458L273.24128,233.58167L272.05197,233.15224zM263.37303,233.25021C261.99438,234.34206 261.04568,235.42781 260.52539,236.50748C260.92893,237.14452 261.44871,237.65821 262.08575,238.04804C263.11263,235.82476 264.85522,233.56898 267.31251,231.28021C266.05163,231.50102 264.73847,232.15785 263.37303,233.25021zM267.66377,251.29032C270.23832,250.53653 273.07276,250.19187 276.1676,250.25735C275.14021,249.61981 273.76868,249.19088 272.05248,248.97008C270.27131,248.73607 268.80841,248.82034 267.66377,249.22337L267.66377,251.29032zM266.02574,256.01049L265.51814,257.4734L263.97758,257.55106L263.54866,258.50636L264.56284,259.61801L263.97758,261.08142L263.80195,261.08142C263.85474,261.08142 264.51056,261.65348 265.77194,262.79711C268.63278,265.60566 270.12106,268.15432 270.23832,270.44309C270.92713,270.44309 271.44082,270.52735 271.77888,270.69638L272.05197,270.44309L273.24179,270.01366L273.84583,270.52126C276.99245,266.28178 278.96904,261.52963 279.77562,256.26378L278.81981,256.26378L278.31271,255.15265L278.31271,253.68974L277.45487,252.90956C275.67319,254.40444 272.83875,255.15265 268.95155,255.15265C267.57291,255.15265 266.59781,255.09377 266.02574,254.97702L266.02574,256.01049zM248.76531,215.98977C258.62087,215.98977 267.00744,219.48054 273.924,226.46308C280.91924,233.51061 284.41711,241.95555 284.41711,251.79792C284.41711,261.65348 280.91924,270.07203 273.924,277.05458C267.00694,283.98434 258.62087,287.44972 248.76531,287.44972C238.85746,287.44972 230.41251,283.98485 223.43047,277.05458C216.44843,270.07203 212.95716,261.65348 212.95716,251.79792C212.95716,241.95504 216.44793,233.51061 223.43047,226.46308C230.478,219.48054 238.92294,215.98977 248.76531,215.98977zM248.76531,213.84465C238.35037,213.84465 229.41813,217.56282 221.96808,225.00069C214.51803,232.38576 210.79275,241.318 210.79275,251.79792C210.79275,262.27732 214.51803,271.24256 221.96808,278.6921C229.41813,286.07717 238.35037,289.76997 248.76531,289.76997C259.19294,289.76997 268.12569,286.07717 275.56254,278.6921C282.94812,271.24205 286.64091,262.27682 286.64091,251.79792C286.64091,241.318 282.94812,232.38576 275.56254,225.00069C268.12569,217.56282 259.19294,213.84465 248.76531,213.84465zM248.76531,204.03426C261.88474,204.03426 273.10524,208.70215 282.42732,218.03794C291.76361,227.43869 296.431,238.69117 296.431,251.79792C296.431,264.91684 291.76361,276.16983 282.42732,285.5579C273.10524,294.89317 261.88423,299.56056 248.76531,299.56056C235.65907,299.56056 224.40608,294.89317 215.00533,285.5579C205.67005,276.22212 201.00216,264.96862 201.00216,251.79792C201.00216,238.69168 205.67005,227.43869 215.00533,218.03794C224.40608,208.70215 235.65907,204.03426 248.76531,204.03426zM265.08973,214.35124C257.35289,210.91884 249.246,210.00212 240.76908,211.60157C232.52565,213.26548 225.40047,217.15979 219.39353,223.28398C225.63447,217.84911 232.85103,214.29946 241.04217,212.63504C249.57138,210.97062 257.5874,211.54319 265.08973,214.35124zM266.02574,212.031C257.66506,208.48135 249.13586,207.56462 240.43762,209.28082C231.44041,211.0625 223.85331,215.1837 217.67733,221.64545C224.13959,215.80754 231.75207,212.031 240.51579,210.31429C249.279,208.53262 257.78232,209.10519 266.02574,212.031zM267.15718,209.53411C258.39398,205.64691 249.25971,204.67841 239.7554,206.6281C230.35465,208.39607 222.33913,212.7457 215.70785,219.67546C222.68989,213.48679 230.79017,209.47523 240.0087,207.64229C249.39575,205.87381 258.44524,206.50425 267.15718,209.53411zM248.76531,201.88914C234.97026,201.88914 223.20307,206.75855 213.46476,216.49686C203.72594,226.23568 198.85653,238.00236 198.85653,251.79792C198.85653,265.59297 203.72594,277.35965 213.46476,287.09847C223.20307,296.83728 234.97026,301.70568 248.76531,301.70568C262.50807,301.70568 274.24937,296.83678 283.98819,287.09847C293.71381,277.35965 298.57611,265.59297 298.57611,251.79792C298.57611,238.00236 293.71381,226.23568 283.98819,216.49686C274.24937,206.75805 262.50807,201.88914 248.76531,201.88914zM256.48844,267.69291L255.47426,266.58127C255.29305,266.7503 254.97377,266.91933 254.51896,267.08785L254.44129,268.62892L252.97788,269.15531L252.4515,269.15531C252.56825,269.72737 252.62713,270.66948 252.62713,271.98315C252.62713,275.88405 251.91243,278.74438 250.4815,280.56464C250.88505,280.96716 251.11194,281.26005 251.16473,281.44228L252.12054,281.44228L253.23168,281.94937L253.23168,282.88538C258.38078,282.1448 263.16542,280.11642 267.58611,276.80078L267.05922,276.2744L267.58611,274.90946L268.09269,274.38257C267.92366,274.04451 267.8394,273.53133 267.8394,272.84201C265.65469,272.72526 263.13293,271.23647 260.2726,268.37563L258.5559,266.40564L258.04881,266.83507L256.48844,267.69291zM267.66377,270.77404C265.09024,268.71979 263.23039,266.57467 262.08626,264.33818L260.5259,265.87875C261.21522,266.91933 262.27509,267.9528 263.7055,268.97968S266.45517,270.60552 267.66377,270.77404zM279.85328,281.69557C273.39153,287.53348 265.74606,291.33642 256.91737,293.10541C248.2709,294.83429 239.76759,294.23685 231.40741,291.31104C239.71581,294.97744 248.3105,295.92005 257.19046,294.13888C266.17549,292.30594 273.72959,288.15833 279.85328,281.69557zM278.05942,280.05754C272.221,285.38887 265.06333,288.93852 256.5859,290.70649C247.99172,292.3704 239.94322,291.79834 232.44139,288.98978C240.17773,292.48766 248.25162,293.40387 256.66458,291.73945C265.1415,290.02377 272.27379,286.12996 278.05942,280.05754zM239.48181,267.08785L238.89705,266.40513L236.8296,268.62892C234.1383,271.43697 231.61553,272.92627 229.26229,273.0953C229.26229,273.61457 229.21001,273.99223 229.10595,274.22674L230.12014,275.16275L230.54906,276.2744L230.04197,276.95712C234.28043,280.1682 239.05847,282.1453 244.3766,282.88589L244.3766,282.12551L245.68367,281.44278L246.19076,281.44278L246.97094,280.56514C245.52783,278.84844 244.80603,275.98811 244.80603,271.98365C244.80603,270.95678 244.89689,270.01366 245.07911,269.15581L244.80603,269.15581L243.01166,268.4533L243.01166,267.08836L241.97819,266.58177L240.9442,267.69342L239.48181,267.08785zM246.62019,270.01366C246.21715,271.15779 246.13289,272.61409 246.3669,274.38207C246.5877,276.16374 247.04302,277.56726 247.73183,278.59464C247.67955,275.2795 247.99832,272.41918 248.68764,270.01366L246.62019,270.01366zM234.15759,262.79711C233.01346,263.30471 231.90181,264.27981 230.82266,265.72291C229.7303,267.08785 229.04098,268.40152 228.7552,269.66291C230.99169,267.2579 233.25406,265.48282 235.54283,264.33869L234.15759,262.79711zM246.1131,314.07082C245.87909,315.16266 245.30043,317.13977 244.3771,320.00009C243.58372,322.80865 243.24617,325.09691 243.36292,326.86437C243.41469,328.86685 244.04513,330.41453 245.25474,331.50688C246.21665,332.43021 247.21763,332.85913 248.25821,332.79365C248.36227,332.79365 248.07649,332.24798 247.40037,331.15512C246.3603,329.5044 245.69737,327.72932 245.41109,325.83141C244.90399,323.25686 245.30703,319.70721 246.62019,315.18246C246.90597,313.17998 246.93236,312.21097 246.69836,312.27594C246.52882,312.32873 246.3339,312.9277 246.1131,314.07082zM281.84257,283.66557C274.84784,289.85473 266.71456,293.86579 257.44426,295.69924C248.27801,297.53219 239.261,296.90175 230.39323,293.80691C239.09197,297.64284 248.19324,298.64332 257.69806,296.81038C267.03333,294.97693 275.08184,290.59583 281.84257,283.66557zM293.34986,292.94957C293.11535,293.05312 293.79807,293.70945 295.39701,294.91906C299.29792,297.09007 302.13236,299.31996 303.90084,301.60872C304.94091,303.22137 305.68861,304.96955 306.14393,306.85528C306.4297,308.11616 306.63122,308.66284 306.74797,308.49331C307.54135,307.805 307.93728,306.8035 307.93728,305.48984C308.00276,303.94267 307.37841,302.4219 306.06525,300.92651C304.80437,299.61335 302.91203,298.2413 300.38977,296.8114C297.75025,295.43326 295.97568,294.43177 295.06555,293.80792C294.09045,293.17038 293.51839,292.88409 293.34986,292.94957zM281.66744,223.71341C286.02316,229.49904 288.94237,236.11104 290.42456,243.54789C291.97173,250.88068 291.82858,258.12972 289.99513,265.29399C292.28339,258.24647 292.71282,250.97205 291.2819,243.46972C289.73473,235.96739 286.53025,229.38229 281.66744,223.71341zM279.85328,225.35144C283.92322,230.83809 286.67289,237.07904 288.10331,244.07427C289.41596,251.17306 289.24744,257.98658 287.59571,264.51381C289.76773,257.63532 290.19614,250.78982 288.88349,243.97681C287.45307,236.94249 284.443,230.73403 279.85328,225.35144zM283.73439,221.99671C288.42817,228.28994 291.51641,235.30447 292.9986,243.0408C294.54577,250.94616 294.37725,258.61753 292.49151,266.05488C294.94931,258.61753 295.40412,250.92028 293.85645,242.96314C292.37425,235.05726 289.00024,228.06862 283.73439,221.99671zM190.52885,194.16601C189.72278,194.9071 189.29385,195.82383 189.24157,196.91619C189.12482,198.3461 189.72887,199.75063 191.05523,201.12876C192.25164,202.38964 194.13687,203.7028 196.71142,205.06875C198.08955,205.82254 199.923,206.77124 202.21126,207.91537C203.01733,208.42297 203.42037,208.47475 203.42037,208.07171C203.35539,207.73416 202.64019,207.10981 201.27474,206.19969C198.23219,204.53577 195.82718,202.61755 194.0587,200.44654C193.01862,199.06841 192.18667,197.40399 191.56283,195.45379C191.15979,194.25687 190.81513,193.82795 190.52885,194.16601zM168.80254,249.90558C170.46646,248.87871 172.21565,248.19599 174.04859,247.85793C176.62314,247.45489 180.22456,247.82544 184.85337,248.96957C186.86854,249.30763 187.84415,249.39189 187.77867,249.22286C187.66192,249.05383 187.06346,248.85231 185.9843,248.61882C183.51381,247.87721 181.53772,247.30515 180.05553,246.90161C177.1952,246.09605 174.84806,245.7255 173.01461,245.79098C171.06441,245.90722 169.54313,246.53867 168.45078,247.6823C167.59293,248.6579 167.1635,249.68478 167.1635,250.76394C167.16401,250.93347 167.71019,250.64668 168.80254,249.90558zM204.18126,292.94957C204.01223,292.88409 203.44016,293.17038 202.46506,293.80691C201.55494,294.43075 199.72148,295.43225 196.96522,296.81038C194.45615,298.18851 192.59681,299.56005 191.3877,300.92549C190.07454,302.42088 189.4436,303.94165 189.49588,305.48882C189.49588,306.75021 189.87303,307.75119 190.62732,308.49229C190.79635,308.66183 191.02376,308.11565 191.31004,306.85426C191.76485,304.90356 192.50646,303.15487 193.53333,301.60771C195.02872,299.50168 197.83677,297.27128 201.95899,294.91805C203.62239,293.70945 204.36349,293.05312 204.18126,292.94957zM215.78551,280.05754C211.49476,274.10289 208.57606,267.45891 207.0289,260.1251C205.65025,252.805 205.81929,245.56306 207.53599,238.3988C205.24773,245.73159 204.81881,253.0324 206.24872,260.30073C207.74411,267.63403 210.9227,274.21963 215.78551,280.05754zM204.53252,260.65148C202.98535,252.74662 203.15388,245.10115 205.03961,237.71607C202.53004,245.43921 202.10111,253.14306 203.75234,260.82711C205.18225,268.66699 208.56286,275.62315 213.89419,281.69506C209.31716,275.67645 206.19694,268.66141 204.53252,260.65148zM209.50548,259.61801C208.07506,252.68825 208.25069,245.87524 210.03186,239.17898C207.7436,245.82296 207.31468,252.72074 208.74459,259.87181C210.05775,266.63304 213.03533,272.78922 217.67683,278.34135C213.6074,272.95825 210.88361,266.7173 209.50548,259.61801z\" pointer-events=\"bounding-box\" id=\"xe_m45d\"/>\n    </g>\n   </g>\n  </g>\n </g>\n</svg>","printColors":["#25637B"],"printColorNames":["No Name"],"printColorCategories":["No Category"],"cmykValue":[""],"printUnit":"inch","PrintDimension":{"boundheight":"13.00","boundwidth":"12.00"},"printSize":"Full Front","designPrice":0,"webFontPrice":0,"isTransit":0,"noOfLines":[],"scalingPrice":0,"isWhiteBase":false,"customizeImage":"https://www.screenshotsinc.com//designer-tool/designer-assets/screenshotsinc_com/images/capturedImage/cart/ci_58cafb16c18888.95470192.png","totalBackgroundPrice":0,"imagePresent":0},{"url":"https://www.screenshotsinc.com//designer-tool/designer-assets/screenshotsinc_com/images/productTemplate/16/51.png","svg":"","printColors":[],"printColorNames":[],"printColorCategories":[],"cmykValue":[],"printUnit":"inch","PrintDimension":{"boundheight":"12.00","boundwidth":"13.00"},"printSize":"","designPrice":0,"webFontPrice":0,"isTransit":0,"noOfLines":[],"scalingPrice":0,"isWhiteBase":false,"customizeImage":"https://www.screenshotsinc.com//designer-tool/designer-assets/screenshotsinc_com/images/capturedImage/cart/ci_58cafb16c1f828.09582976.png","totalBackgroundPrice":0,"imagePresent":0}],"simpleData":{"_R!@#&":["U{{/U~}",""],"isObject":[1,0],"isMultiBoundObject":[]},"nameNumberData":{},"envInfo":{"browserIp":"72.161.249.232","browserHeight":1080,"browserWidth":1920,"browserLang":"en-US","userAgent":"Mozilla/5.0 (Windows NT 10.0; Win64; x64) AppleWebKit/537.36 (KHTML, like Gecko) Chrome/56.0.2924.87 Safari/537.36","browserName":"Chrome"},"notes":"","multiBoundPriceArr":[],"unitPrice":"0.00"}